{
    "ansible_facts": {
        "ansible_net_all_ipv4_addresses": [
            "172.16.1.13"
        ],
        "ansible_net_all_ipv6_addresses": [],
        "ansible_net_config": "!Command: show running-config\n!Time: Fri Mar 15 14:39:51 2019\n\nversion 7.3(0)D1(1)\npower redundancy-mode redundant\n\nvdc switch id 1\n  limit-resource module-type m1 m1xl m2xl f2e \n  allocate interface Ethernet2/1-48\n  allocate interface Ethernet3/1-48\n  allocate interface Ethernet4/1-48\n  limit-resource vlan minimum 16 maximum 4094\n  limit-resource vrf minimum 2 maximum 4096\n  limit-resource port-channel minimum 0 maximum 768\n  limit-resource u4route-mem minimum 96 maximum 96\n  limit-resource u6route-mem minimum 24 maximum 24\n  limit-resource m4route-mem minimum 58 maximum 58\n  limit-resource m6route-mem minimum 8 maximum 8\nusername admin password 5 $5$Otc7T0NC$K.ulnSZnSyXLrTGNBdtLgZJXEa8EeNx.BrdZ98XyK2C  role network-admin\nno password strength-check\nip domain-lookup\nvlan dot1Q tag native\nsystem default switchport\nsystem jumbomtu 0\nno logging event trunk-status enable\ncopp profile strict\nsnmp-server user admin auth md5 0x328945d53e05e8e7207f8c20b142f0b7 priv 0x328945d53e05e8e7207f8c20b142f0b7 localizedkey engineID 128:0:0:9:3:0:0:0:0:0:0\nrmon event 1 log description FATAL(1) owner PMON@FATAL\nrmon event 2 log description CRITICAL(2) owner PMON@CRITICAL\nrmon event 3 log description ERROR(3) owner PMON@ERROR\nrmon event 4 log description WARNING(4) owner PMON@WARNING\nrmon event 5 log description INFORMATION(5) owner PMON@INFO\nsnmp-server enable traps link\nsnmp-server enable traps link cisco-xcvr-mon-status-chg\n\nvlan 1\n\nvrf context management\n\ninterface mgmt0\n  vrf member management\n  ip address 172.16.1.13/24\n\ninterface Ethernet2/1\n  shutdown\n  no switchport\n  mac-address 0000.0000.002f\n\ninterface Ethernet2/2\n  shutdown\n  no switchport\n  mac-address 0000.0000.002f\n\ninterface Ethernet2/3\n  shutdown\n  no switchport\n  mac-address 0000.0000.002f\n\ninterface Ethernet2/4\n  shutdown\n  no switchport\n  mac-address 0000.0000.002f\n\ninterface Ethernet2/5\n  shutdown\n  no switchport\n  mac-address 0000.0000.002f\n\ninterface Ethernet2/6\n  shutdown\n  no switchport\n  mac-address 0000.0000.002f\n\ninterface Ethernet2/7\n  shutdown\n  no switchport\n  mac-address 0000.0000.002f\n\ninterface Ethernet2/8\n  shutdown\n  no switchport\n  mac-address 0000.0000.002f\n\ninterface Ethernet2/9\n  shutdown\n  no switchport\n  mac-address 0000.0000.002f\n\ninterface Ethernet2/10\n  shutdown\n  no switchport\n  mac-address 0000.0000.002f\n\ninterface Ethernet2/11\n  shutdown\n  no switchport\n  mac-address 0000.0000.002f\n\ninterface Ethernet2/12\n  shutdown\n  no switchport\n  mac-address 0000.0000.002f\n\ninterface Ethernet2/13\n  shutdown\n  no switchport\n  mac-address 0000.0000.002f\n\ninterface Ethernet2/14\n  shutdown\n  no switchport\n  mac-address 0000.0000.002f\n\ninterface Ethernet2/15\n  shutdown\n  no switchport\n  mac-address 0000.0000.002f\n\ninterface Ethernet2/16\n  shutdown\n  no switchport\n  mac-address 0000.0000.002f\n\ninterface Ethernet2/17\n  shutdown\n  no switchport\n  mac-address 0000.0000.002f\n\ninterface Ethernet2/18\n  shutdown\n  no switchport\n  mac-address 0000.0000.002f\n\ninterface Ethernet2/19\n  shutdown\n  no switchport\n  mac-address 0000.0000.002f\n\ninterface Ethernet2/20\n  shutdown\n  no switchport\n  mac-address 0000.0000.002f\n\ninterface Ethernet2/21\n  shutdown\n  no switchport\n  mac-address 0000.0000.002f\n\ninterface Ethernet2/22\n  shutdown\n  no switchport\n  mac-address 0000.0000.002f\n\ninterface Ethernet2/23\n  shutdown\n  no switchport\n  mac-address 0000.0000.002f\n\ninterface Ethernet2/24\n  shutdown\n  no switchport\n  mac-address 0000.0000.002f\n\ninterface Ethernet2/25\n  shutdown\n  no switchport\n  mac-address 0000.0000.002f\n\ninterface Ethernet2/26\n  shutdown\n  no switchport\n  mac-address 0000.0000.002f\n\ninterface Ethernet2/27\n  shutdown\n  no switchport\n  mac-address 0000.0000.002f\n\ninterface Ethernet2/28\n  shutdown\n  no switchport\n  mac-address 0000.0000.002f\n\ninterface Ethernet2/29\n  shutdown\n  no switchport\n  mac-address 0000.0000.002f\n\ninterface Ethernet2/30\n  shutdown\n  no switchport\n  mac-address 0000.0000.002f\n\ninterface Ethernet2/31\n  shutdown\n  no switchport\n  mac-address 0000.0000.002f\n\ninterface Ethernet2/32\n  shutdown\n  no switchport\n  mac-address 0000.0000.002f\n\ninterface Ethernet2/33\n  shutdown\n  no switchport\n  mac-address 0000.0000.002f\n\ninterface Ethernet2/34\n  shutdown\n  no switchport\n  mac-address 0000.0000.002f\n\ninterface Ethernet2/35\n  shutdown\n  no switchport\n  mac-address 0000.0000.002f\n\ninterface Ethernet2/36\n  shutdown\n  no switchport\n  mac-address 0000.0000.002f\n\ninterface Ethernet2/37\n  shutdown\n  no switchport\n  mac-address 0000.0000.002f\n\ninterface Ethernet2/38\n  shutdown\n  no switchport\n  mac-address 0000.0000.002f\n\ninterface Ethernet2/39\n  shutdown\n  no switchport\n  mac-address 0000.0000.002f\n\ninterface Ethernet2/40\n  shutdown\n  no switchport\n  mac-address 0000.0000.002f\n\ninterface Ethernet2/41\n  shutdown\n  no switchport\n  mac-address 0000.0000.002f\n\ninterface Ethernet2/42\n  shutdown\n  no switchport\n  mac-address 0000.0000.002f\n\ninterface Ethernet2/43\n  shutdown\n  no switchport\n  mac-address 0000.0000.002f\n\ninterface Ethernet2/44\n  shutdown\n  no switchport\n  mac-address 0000.0000.002f\n\ninterface Ethernet2/45\n  shutdown\n  no switchport\n  mac-address 0000.0000.002f\n\ninterface Ethernet2/46\n  shutdown\n  no switchport\n  mac-address 0000.0000.002f\n\ninterface Ethernet2/47\n  shutdown\n  no switchport\n  mac-address 0000.0000.002f\n\ninterface Ethernet2/48\n  shutdown\n  no switchport\n  mac-address 0000.0000.002f\n\ninterface Ethernet3/1\n  shutdown\n  no switchport\n  medium p2p\n\ninterface Ethernet3/2\n  shutdown\n  no switchport\n  medium p2p\n\ninterface Ethernet3/3\n  shutdown\n  no switchport\n  medium p2p\n\ninterface Ethernet3/4\n  shutdown\n  no switchport\n  medium p2p\n\ninterface Ethernet3/5\n  shutdown\n  no switchport\n  medium p2p\n\ninterface Ethernet3/6\n  shutdown\n  no switchport\n  medium p2p\n\ninterface Ethernet3/7\n  shutdown\n  no switchport\n  medium p2p\n\ninterface Ethernet3/8\n  shutdown\n  no switchport\n  medium p2p\n\ninterface Ethernet3/9\n  shutdown\n  no switchport\n  medium p2p\n\ninterface Ethernet3/10\n  shutdown\n  no switchport\n  medium p2p\n\ninterface Ethernet3/11\n  shutdown\n  no switchport\n  medium p2p\n\ninterface Ethernet3/12\n  shutdown\n  no switchport\n  medium p2p\n\ninterface Ethernet3/13\n  shutdown\n  no switchport\n  medium p2p\n\ninterface Ethernet3/14\n  shutdown\n  no switchport\n  medium p2p\n\ninterface Ethernet3/15\n  shutdown\n  no switchport\n  medium p2p\n\ninterface Ethernet3/16\n  shutdown\n  no switchport\n  medium p2p\n\ninterface Ethernet3/17\n  shutdown\n  no switchport\n  medium p2p\n\ninterface Ethernet3/18\n  shutdown\n  no switchport\n  medium p2p\n\ninterface Ethernet3/19\n  shutdown\n  no switchport\n  medium p2p\n\ninterface Ethernet3/20\n  shutdown\n  no switchport\n  medium p2p\n\ninterface Ethernet3/21\n  shutdown\n  no switchport\n  medium p2p\n\ninterface Ethernet3/22\n  shutdown\n  no switchport\n  medium p2p\n\ninterface Ethernet3/23\n  shutdown\n  no switchport\n  medium p2p\n\ninterface Ethernet3/24\n  shutdown\n  no switchport\n  medium p2p\n\ninterface Ethernet3/25\n  shutdown\n  no switchport\n  medium p2p\n\ninterface Ethernet3/26\n  shutdown\n  no switchport\n  medium p2p\n\ninterface Ethernet3/27\n  shutdown\n  no switchport\n  medium p2p\n\ninterface Ethernet3/28\n  shutdown\n  no switchport\n  medium p2p\n\ninterface Ethernet3/29\n  shutdown\n  no switchport\n  medium p2p\n\ninterface Ethernet3/30\n  shutdown\n  no switchport\n  medium p2p\n\ninterface Ethernet3/31\n  shutdown\n  no switchport\n  medium p2p\n\ninterface Ethernet3/32\n  shutdown\n  no switchport\n  medium p2p\n\ninterface Ethernet3/33\n  shutdown\n  no switchport\n  medium p2p\n\ninterface Ethernet3/34\n  shutdown\n  no switchport\n  medium p2p\n\ninterface Ethernet3/35\n  shutdown\n  no switchport\n  medium p2p\n\ninterface Ethernet3/36\n  shutdown\n  no switchport\n  medium p2p\n\ninterface Ethernet3/37\n  shutdown\n  no switchport\n  medium p2p\n\ninterface Ethernet3/38\n  shutdown\n  no switchport\n  medium p2p\n\ninterface Ethernet3/39\n  shutdown\n  no switchport\n  medium p2p\n\ninterface Ethernet3/40\n  shutdown\n  no switchport\n  medium p2p\n\ninterface Ethernet3/41\n  shutdown\n  no switchport\n  medium p2p\n\ninterface Ethernet3/42\n  shutdown\n  no switchport\n  medium p2p\n\ninterface Ethernet3/43\n  shutdown\n  no switchport\n  medium p2p\n\ninterface Ethernet3/44\n  shutdown\n  no switchport\n  medium p2p\n\ninterface Ethernet3/45\n  shutdown\n  no switchport\n  medium p2p\n\ninterface Ethernet3/46\n  shutdown\n  no switchport\n  medium p2p\n\ninterface Ethernet3/47\n  shutdown\n  no switchport\n  medium p2p\n\ninterface Ethernet3/48\n  shutdown\n  no switchport\n  medium p2p\n\ninterface Ethernet4/1\n  switchport\n  no shutdown\n\ninterface Ethernet4/2\n  switchport\n  no shutdown\n\ninterface Ethernet4/3\n  switchport\n  no shutdown\n\ninterface Ethernet4/4\n  switchport\n  no shutdown\n\ninterface Ethernet4/5\n  switchport\n  no shutdown\n\ninterface Ethernet4/6\n  switchport\n  no shutdown\n\ninterface Ethernet4/7\n  switchport\n  no shutdown\n\ninterface Ethernet4/8\n  switchport\n  no shutdown\n\ninterface Ethernet4/9\n  switchport\n  no shutdown\n\ninterface Ethernet4/10\n  switchport\n  no shutdown\n\ninterface Ethernet4/11\n  switchport\n  no shutdown\n\ninterface Ethernet4/12\n  switchport\n  no shutdown\n\ninterface Ethernet4/13\n  switchport\n  no shutdown\n\ninterface Ethernet4/14\n  switchport\n  no shutdown\n\ninterface Ethernet4/15\n  switchport\n  no shutdown\n\ninterface Ethernet4/16\n  switchport\n  no shutdown\n\ninterface Ethernet4/17\n  switchport\n  no shutdown\n\ninterface Ethernet4/18\n  switchport\n  no shutdown\n\ninterface Ethernet4/19\n  switchport\n  no shutdown\n\ninterface Ethernet4/20\n  switchport\n  no shutdown\n\ninterface Ethernet4/21\n  switchport\n  no shutdown\n\ninterface Ethernet4/22\n  switchport\n  no shutdown\n\ninterface Ethernet4/23\n  switchport\n  no shutdown\n\ninterface Ethernet4/24\n  switchport\n  no shutdown\n\ninterface Ethernet4/25\n  switchport\n  no shutdown\n\ninterface Ethernet4/26\n  switchport\n  no shutdown\n\ninterface Ethernet4/27\n  switchport\n  no shutdown\n\ninterface Ethernet4/28\n  switchport\n  no shutdown\n\ninterface Ethernet4/29\n  switchport\n  no shutdown\n\ninterface Ethernet4/30\n  switchport\n  no shutdown\n\ninterface Ethernet4/31\n  switchport\n  no shutdown\n\ninterface Ethernet4/32\n  switchport\n  no shutdown\n\ninterface Ethernet4/33\n  switchport\n  no shutdown\n\ninterface Ethernet4/34\n  switchport\n  no shutdown\n\ninterface Ethernet4/35\n  switchport\n  no shutdown\n\ninterface Ethernet4/36\n  switchport\n  no shutdown\n\ninterface Ethernet4/37\n  switchport\n  no shutdown\n\ninterface Ethernet4/38\n  switchport\n  no shutdown\n\ninterface Ethernet4/39\n  switchport\n  no shutdown\n\ninterface Ethernet4/40\n  switchport\n  no shutdown\n\ninterface Ethernet4/41\n  switchport\n  no shutdown\n\ninterface Ethernet4/42\n  switchport\n  no shutdown\n\ninterface Ethernet4/43\n  switchport\n  no shutdown\n\ninterface Ethernet4/44\n  switchport\n  no shutdown\n\ninterface Ethernet4/45\n  switchport\n  no shutdown\n\ninterface Ethernet4/46\n  switchport\n  no shutdown\n\ninterface Ethernet4/47\n  switchport\n  no shutdown\n\ninterface Ethernet4/48\n  switchport\n  no shutdown\nline console\nline vty\nboot kickstart bootflash:/titanium-d1-kickstart.7.3.0.D1.1.bin\nboot system bootflash:/titanium-d1.7.3.0.D1.1.bin",
        "ansible_net_filesystems": [
            "bootflash:"
        ],
        "ansible_net_gather_subset": [
            "hardware",
            "default",
            "interfaces",
            "legacy",
            "config"
        ],
        "ansible_net_hostname": "switch",
        "ansible_net_image": "bootflash:///titanium-d1.7.3.0.D1.1.bin",
        "ansible_net_interfaces": {
            "Ethernet2/1": {
                "bandwidth": 1000000,
                "duplex": "auto",
                "macaddress": "0000.0000.002f",
                "mode": "routed",
                "mtu": "1500",
                "speed": "auto-speed",
                "state": "down",
                "type": "Ethernet"
            },
            "Ethernet2/10": {
                "bandwidth": 1000000,
                "duplex": "auto",
                "macaddress": "0000.0000.002f",
                "mode": "routed",
                "mtu": "1500",
                "speed": "auto-speed",
                "state": "down",
                "type": "Ethernet"
            },
            "Ethernet2/11": {
                "bandwidth": 1000000,
                "duplex": "auto",
                "macaddress": "0000.0000.002f",
                "mode": "routed",
                "mtu": "1500",
                "speed": "auto-speed",
                "state": "down",
                "type": "Ethernet"
            },
            "Ethernet2/12": {
                "bandwidth": 1000000,
                "duplex": "auto",
                "macaddress": "0000.0000.002f",
                "mode": "routed",
                "mtu": "1500",
                "speed": "auto-speed",
                "state": "down",
                "type": "Ethernet"
            },
            "Ethernet2/13": {
                "bandwidth": 1000000,
                "duplex": "auto",
                "macaddress": "0000.0000.002f",
                "mode": "routed",
                "mtu": "1500",
                "speed": "auto-speed",
                "state": "down",
                "type": "Ethernet"
            },
            "Ethernet2/14": {
                "bandwidth": 1000000,
                "duplex": "auto",
                "macaddress": "0000.0000.002f",
                "mode": "routed",
                "mtu": "1500",
                "speed": "auto-speed",
                "state": "down",
                "type": "Ethernet"
            },
            "Ethernet2/15": {
                "bandwidth": 1000000,
                "duplex": "auto",
                "macaddress": "0000.0000.002f",
                "mode": "routed",
                "mtu": "1500",
                "speed": "auto-speed",
                "state": "down",
                "type": "Ethernet"
            },
            "Ethernet2/16": {
                "bandwidth": 1000000,
                "duplex": "auto",
                "macaddress": "0000.0000.002f",
                "mode": "routed",
                "mtu": "1500",
                "speed": "auto-speed",
                "state": "down",
                "type": "Ethernet"
            },
            "Ethernet2/17": {
                "bandwidth": 1000000,
                "duplex": "auto",
                "macaddress": "0000.0000.002f",
                "mode": "routed",
                "mtu": "1500",
                "speed": "auto-speed",
                "state": "down",
                "type": "Ethernet"
            },
            "Ethernet2/18": {
                "bandwidth": 1000000,
                "duplex": "auto",
                "macaddress": "0000.0000.002f",
                "mode": "routed",
                "mtu": "1500",
                "speed": "auto-speed",
                "state": "down",
                "type": "Ethernet"
            },
            "Ethernet2/19": {
                "bandwidth": 1000000,
                "duplex": "auto",
                "macaddress": "0000.0000.002f",
                "mode": "routed",
                "mtu": "1500",
                "speed": "auto-speed",
                "state": "down",
                "type": "Ethernet"
            },
            "Ethernet2/2": {
                "bandwidth": 1000000,
                "duplex": "auto",
                "macaddress": "0000.0000.002f",
                "mode": "routed",
                "mtu": "1500",
                "speed": "auto-speed",
                "state": "down",
                "type": "Ethernet"
            },
            "Ethernet2/20": {
                "bandwidth": 1000000,
                "duplex": "auto",
                "macaddress": "0000.0000.002f",
                "mode": "routed",
                "mtu": "1500",
                "speed": "auto-speed",
                "state": "down",
                "type": "Ethernet"
            },
            "Ethernet2/21": {
                "bandwidth": 1000000,
                "duplex": "auto",
                "macaddress": "0000.0000.002f",
                "mode": "routed",
                "mtu": "1500",
                "speed": "auto-speed",
                "state": "down",
                "type": "Ethernet"
            },
            "Ethernet2/22": {
                "bandwidth": 1000000,
                "duplex": "auto",
                "macaddress": "0000.0000.002f",
                "mode": "routed",
                "mtu": "1500",
                "speed": "auto-speed",
                "state": "down",
                "type": "Ethernet"
            },
            "Ethernet2/23": {
                "bandwidth": 1000000,
                "duplex": "auto",
                "macaddress": "0000.0000.002f",
                "mode": "routed",
                "mtu": "1500",
                "speed": "auto-speed",
                "state": "down",
                "type": "Ethernet"
            },
            "Ethernet2/24": {
                "bandwidth": 1000000,
                "duplex": "auto",
                "macaddress": "0000.0000.002f",
                "mode": "routed",
                "mtu": "1500",
                "speed": "auto-speed",
                "state": "down",
                "type": "Ethernet"
            },
            "Ethernet2/25": {
                "bandwidth": 1000000,
                "duplex": "auto",
                "macaddress": "0000.0000.002f",
                "mode": "routed",
                "mtu": "1500",
                "speed": "auto-speed",
                "state": "down",
                "type": "Ethernet"
            },
            "Ethernet2/26": {
                "bandwidth": 1000000,
                "duplex": "auto",
                "macaddress": "0000.0000.002f",
                "mode": "routed",
                "mtu": "1500",
                "speed": "auto-speed",
                "state": "down",
                "type": "Ethernet"
            },
            "Ethernet2/27": {
                "bandwidth": 1000000,
                "duplex": "auto",
                "macaddress": "0000.0000.002f",
                "mode": "routed",
                "mtu": "1500",
                "speed": "auto-speed",
                "state": "down",
                "type": "Ethernet"
            },
            "Ethernet2/28": {
                "bandwidth": 1000000,
                "duplex": "auto",
                "macaddress": "0000.0000.002f",
                "mode": "routed",
                "mtu": "1500",
                "speed": "auto-speed",
                "state": "down",
                "type": "Ethernet"
            },
            "Ethernet2/29": {
                "bandwidth": 1000000,
                "duplex": "auto",
                "macaddress": "0000.0000.002f",
                "mode": "routed",
                "mtu": "1500",
                "speed": "auto-speed",
                "state": "down",
                "type": "Ethernet"
            },
            "Ethernet2/3": {
                "bandwidth": 1000000,
                "duplex": "auto",
                "macaddress": "0000.0000.002f",
                "mode": "routed",
                "mtu": "1500",
                "speed": "auto-speed",
                "state": "down",
                "type": "Ethernet"
            },
            "Ethernet2/30": {
                "bandwidth": 1000000,
                "duplex": "auto",
                "macaddress": "0000.0000.002f",
                "mode": "routed",
                "mtu": "1500",
                "speed": "auto-speed",
                "state": "down",
                "type": "Ethernet"
            },
            "Ethernet2/31": {
                "bandwidth": 1000000,
                "duplex": "auto",
                "macaddress": "0000.0000.002f",
                "mode": "routed",
                "mtu": "1500",
                "speed": "auto-speed",
                "state": "down",
                "type": "Ethernet"
            },
            "Ethernet2/32": {
                "bandwidth": 1000000,
                "duplex": "auto",
                "macaddress": "0000.0000.002f",
                "mode": "routed",
                "mtu": "1500",
                "speed": "auto-speed",
                "state": "down",
                "type": "Ethernet"
            },
            "Ethernet2/33": {
                "bandwidth": 1000000,
                "duplex": "auto",
                "macaddress": "0000.0000.002f",
                "mode": "routed",
                "mtu": "1500",
                "speed": "auto-speed",
                "state": "down",
                "type": "Ethernet"
            },
            "Ethernet2/34": {
                "bandwidth": 1000000,
                "duplex": "auto",
                "macaddress": "0000.0000.002f",
                "mode": "routed",
                "mtu": "1500",
                "speed": "auto-speed",
                "state": "down",
                "type": "Ethernet"
            },
            "Ethernet2/35": {
                "bandwidth": 1000000,
                "duplex": "auto",
                "macaddress": "0000.0000.002f",
                "mode": "routed",
                "mtu": "1500",
                "speed": "auto-speed",
                "state": "down",
                "type": "Ethernet"
            },
            "Ethernet2/36": {
                "bandwidth": 1000000,
                "duplex": "auto",
                "macaddress": "0000.0000.002f",
                "mode": "routed",
                "mtu": "1500",
                "speed": "auto-speed",
                "state": "down",
                "type": "Ethernet"
            },
            "Ethernet2/37": {
                "bandwidth": 1000000,
                "duplex": "auto",
                "macaddress": "0000.0000.002f",
                "mode": "routed",
                "mtu": "1500",
                "speed": "auto-speed",
                "state": "down",
                "type": "Ethernet"
            },
            "Ethernet2/38": {
                "bandwidth": 1000000,
                "duplex": "auto",
                "macaddress": "0000.0000.002f",
                "mode": "routed",
                "mtu": "1500",
                "speed": "auto-speed",
                "state": "down",
                "type": "Ethernet"
            },
            "Ethernet2/39": {
                "bandwidth": 1000000,
                "duplex": "auto",
                "macaddress": "0000.0000.002f",
                "mode": "routed",
                "mtu": "1500",
                "speed": "auto-speed",
                "state": "down",
                "type": "Ethernet"
            },
            "Ethernet2/4": {
                "bandwidth": 1000000,
                "duplex": "auto",
                "macaddress": "0000.0000.002f",
                "mode": "routed",
                "mtu": "1500",
                "speed": "auto-speed",
                "state": "down",
                "type": "Ethernet"
            },
            "Ethernet2/40": {
                "bandwidth": 1000000,
                "duplex": "auto",
                "macaddress": "0000.0000.002f",
                "mode": "routed",
                "mtu": "1500",
                "speed": "auto-speed",
                "state": "down",
                "type": "Ethernet"
            },
            "Ethernet2/41": {
                "bandwidth": 1000000,
                "duplex": "auto",
                "macaddress": "0000.0000.002f",
                "mode": "routed",
                "mtu": "1500",
                "speed": "auto-speed",
                "state": "down",
                "type": "Ethernet"
            },
            "Ethernet2/42": {
                "bandwidth": 1000000,
                "duplex": "auto",
                "macaddress": "0000.0000.002f",
                "mode": "routed",
                "mtu": "1500",
                "speed": "auto-speed",
                "state": "down",
                "type": "Ethernet"
            },
            "Ethernet2/43": {
                "bandwidth": 1000000,
                "duplex": "auto",
                "macaddress": "0000.0000.002f",
                "mode": "routed",
                "mtu": "1500",
                "speed": "auto-speed",
                "state": "down",
                "type": "Ethernet"
            },
            "Ethernet2/44": {
                "bandwidth": 1000000,
                "duplex": "auto",
                "macaddress": "0000.0000.002f",
                "mode": "routed",
                "mtu": "1500",
                "speed": "auto-speed",
                "state": "down",
                "type": "Ethernet"
            },
            "Ethernet2/45": {
                "bandwidth": 1000000,
                "duplex": "auto",
                "macaddress": "0000.0000.002f",
                "mode": "routed",
                "mtu": "1500",
                "speed": "auto-speed",
                "state": "down",
                "type": "Ethernet"
            },
            "Ethernet2/46": {
                "bandwidth": 1000000,
                "duplex": "auto",
                "macaddress": "0000.0000.002f",
                "mode": "routed",
                "mtu": "1500",
                "speed": "auto-speed",
                "state": "down",
                "type": "Ethernet"
            },
            "Ethernet2/47": {
                "bandwidth": 1000000,
                "duplex": "auto",
                "macaddress": "0000.0000.002f",
                "mode": "routed",
                "mtu": "1500",
                "speed": "auto-speed",
                "state": "down",
                "type": "Ethernet"
            },
            "Ethernet2/48": {
                "bandwidth": 1000000,
                "duplex": "auto",
                "macaddress": "0000.0000.002f",
                "mode": "routed",
                "mtu": "1500",
                "speed": "auto-speed",
                "state": "down",
                "type": "Ethernet"
            },
            "Ethernet2/5": {
                "bandwidth": 1000000,
                "duplex": "auto",
                "macaddress": "0000.0000.002f",
                "mode": "routed",
                "mtu": "1500",
                "speed": "auto-speed",
                "state": "down",
                "type": "Ethernet"
            },
            "Ethernet2/6": {
                "bandwidth": 1000000,
                "duplex": "auto",
                "macaddress": "0000.0000.002f",
                "mode": "routed",
                "mtu": "1500",
                "speed": "auto-speed",
                "state": "down",
                "type": "Ethernet"
            },
            "Ethernet2/7": {
                "bandwidth": 1000000,
                "duplex": "auto",
                "macaddress": "0000.0000.002f",
                "mode": "routed",
                "mtu": "1500",
                "speed": "auto-speed",
                "state": "down",
                "type": "Ethernet"
            },
            "Ethernet2/8": {
                "bandwidth": 1000000,
                "duplex": "auto",
                "macaddress": "0000.0000.002f",
                "mode": "routed",
                "mtu": "1500",
                "speed": "auto-speed",
                "state": "down",
                "type": "Ethernet"
            },
            "Ethernet2/9": {
                "bandwidth": 1000000,
                "duplex": "auto",
                "macaddress": "0000.0000.002f",
                "mode": "routed",
                "mtu": "1500",
                "speed": "auto-speed",
                "state": "down",
                "type": "Ethernet"
            },
            "Ethernet3/1": {
                "bandwidth": 1000000,
                "duplex": "auto",
                "macaddress": "fa16.3e88.4af6",
                "mode": "routed",
                "mtu": "1500",
                "speed": "auto-speed",
                "state": "down",
                "type": "Ethernet"
            },
            "Ethernet3/10": {
                "bandwidth": 1000000,
                "duplex": "auto",
                "macaddress": "fa16.3e88.4af6",
                "mode": "routed",
                "mtu": "1500",
                "speed": "auto-speed",
                "state": "down",
                "type": "Ethernet"
            },
            "Ethernet3/11": {
                "bandwidth": 1000000,
                "duplex": "auto",
                "macaddress": "fa16.3e88.4af6",
                "mode": "routed",
                "mtu": "1500",
                "speed": "auto-speed",
                "state": "down",
                "type": "Ethernet"
            },
            "Ethernet3/12": {
                "bandwidth": 1000000,
                "duplex": "auto",
                "macaddress": "fa16.3e88.4af6",
                "mode": "routed",
                "mtu": "1500",
                "speed": "auto-speed",
                "state": "down",
                "type": "Ethernet"
            },
            "Ethernet3/13": {
                "bandwidth": 1000000,
                "duplex": "auto",
                "macaddress": "fa16.3e88.4af6",
                "mode": "routed",
                "mtu": "1500",
                "speed": "auto-speed",
                "state": "down",
                "type": "Ethernet"
            },
            "Ethernet3/14": {
                "bandwidth": 1000000,
                "duplex": "auto",
                "macaddress": "fa16.3e88.4af6",
                "mode": "routed",
                "mtu": "1500",
                "speed": "auto-speed",
                "state": "down",
                "type": "Ethernet"
            },
            "Ethernet3/15": {
                "bandwidth": 1000000,
                "duplex": "auto",
                "macaddress": "fa16.3e88.4af6",
                "mode": "routed",
                "mtu": "1500",
                "speed": "auto-speed",
                "state": "down",
                "type": "Ethernet"
            },
            "Ethernet3/16": {
                "bandwidth": 1000000,
                "duplex": "auto",
                "macaddress": "fa16.3e88.4af6",
                "mode": "routed",
                "mtu": "1500",
                "speed": "auto-speed",
                "state": "down",
                "type": "Ethernet"
            },
            "Ethernet3/17": {
                "bandwidth": 1000000,
                "duplex": "auto",
                "macaddress": "fa16.3e88.4af6",
                "mode": "routed",
                "mtu": "1500",
                "speed": "auto-speed",
                "state": "down",
                "type": "Ethernet"
            },
            "Ethernet3/18": {
                "bandwidth": 1000000,
                "duplex": "auto",
                "macaddress": "fa16.3e88.4af6",
                "mode": "routed",
                "mtu": "1500",
                "speed": "auto-speed",
                "state": "down",
                "type": "Ethernet"
            },
            "Ethernet3/19": {
                "bandwidth": 1000000,
                "duplex": "auto",
                "macaddress": "fa16.3e88.4af6",
                "mode": "routed",
                "mtu": "1500",
                "speed": "auto-speed",
                "state": "down",
                "type": "Ethernet"
            },
            "Ethernet3/2": {
                "bandwidth": 1000000,
                "duplex": "auto",
                "macaddress": "fa16.3e88.4af6",
                "mode": "routed",
                "mtu": "1500",
                "speed": "auto-speed",
                "state": "down",
                "type": "Ethernet"
            },
            "Ethernet3/20": {
                "bandwidth": 1000000,
                "duplex": "auto",
                "macaddress": "fa16.3e88.4af6",
                "mode": "routed",
                "mtu": "1500",
                "speed": "auto-speed",
                "state": "down",
                "type": "Ethernet"
            },
            "Ethernet3/21": {
                "bandwidth": 1000000,
                "duplex": "auto",
                "macaddress": "fa16.3e88.4af6",
                "mode": "routed",
                "mtu": "1500",
                "speed": "auto-speed",
                "state": "down",
                "type": "Ethernet"
            },
            "Ethernet3/22": {
                "bandwidth": 1000000,
                "duplex": "auto",
                "macaddress": "fa16.3e88.4af6",
                "mode": "routed",
                "mtu": "1500",
                "speed": "auto-speed",
                "state": "down",
                "type": "Ethernet"
            },
            "Ethernet3/23": {
                "bandwidth": 1000000,
                "duplex": "auto",
                "macaddress": "fa16.3e88.4af6",
                "mode": "routed",
                "mtu": "1500",
                "speed": "auto-speed",
                "state": "down",
                "type": "Ethernet"
            },
            "Ethernet3/24": {
                "bandwidth": 1000000,
                "duplex": "auto",
                "macaddress": "fa16.3e88.4af6",
                "mode": "routed",
                "mtu": "1500",
                "speed": "auto-speed",
                "state": "down",
                "type": "Ethernet"
            },
            "Ethernet3/25": {
                "bandwidth": 1000000,
                "duplex": "auto",
                "macaddress": "fa16.3e88.4af6",
                "mode": "routed",
                "mtu": "1500",
                "speed": "auto-speed",
                "state": "down",
                "type": "Ethernet"
            },
            "Ethernet3/26": {
                "bandwidth": 1000000,
                "duplex": "auto",
                "macaddress": "fa16.3e88.4af6",
                "mode": "routed",
                "mtu": "1500",
                "speed": "auto-speed",
                "state": "down",
                "type": "Ethernet"
            },
            "Ethernet3/27": {
                "bandwidth": 1000000,
                "duplex": "auto",
                "macaddress": "fa16.3e88.4af6",
                "mode": "routed",
                "mtu": "1500",
                "speed": "auto-speed",
                "state": "down",
                "type": "Ethernet"
            },
            "Ethernet3/28": {
                "bandwidth": 1000000,
                "duplex": "auto",
                "macaddress": "fa16.3e88.4af6",
                "mode": "routed",
                "mtu": "1500",
                "speed": "auto-speed",
                "state": "down",
                "type": "Ethernet"
            },
            "Ethernet3/29": {
                "bandwidth": 1000000,
                "duplex": "auto",
                "macaddress": "fa16.3e88.4af6",
                "mode": "routed",
                "mtu": "1500",
                "speed": "auto-speed",
                "state": "down",
                "type": "Ethernet"
            },
            "Ethernet3/3": {
                "bandwidth": 1000000,
                "duplex": "auto",
                "macaddress": "fa16.3e88.4af6",
                "mode": "routed",
                "mtu": "1500",
                "speed": "auto-speed",
                "state": "down",
                "type": "Ethernet"
            },
            "Ethernet3/30": {
                "bandwidth": 1000000,
                "duplex": "auto",
                "macaddress": "fa16.3e88.4af6",
                "mode": "routed",
                "mtu": "1500",
                "speed": "auto-speed",
                "state": "down",
                "type": "Ethernet"
            },
            "Ethernet3/31": {
                "bandwidth": 1000000,
                "duplex": "auto",
                "macaddress": "fa16.3e88.4af6",
                "mode": "routed",
                "mtu": "1500",
                "speed": "auto-speed",
                "state": "down",
                "type": "Ethernet"
            },
            "Ethernet3/32": {
                "bandwidth": 1000000,
                "duplex": "auto",
                "macaddress": "fa16.3e88.4af6",
                "mode": "routed",
                "mtu": "1500",
                "speed": "auto-speed",
                "state": "down",
                "type": "Ethernet"
            },
            "Ethernet3/33": {
                "bandwidth": 1000000,
                "duplex": "auto",
                "macaddress": "fa16.3e88.4af6",
                "mode": "routed",
                "mtu": "1500",
                "speed": "auto-speed",
                "state": "down",
                "type": "Ethernet"
            },
            "Ethernet3/34": {
                "bandwidth": 1000000,
                "duplex": "auto",
                "macaddress": "fa16.3e88.4af6",
                "mode": "routed",
                "mtu": "1500",
                "speed": "auto-speed",
                "state": "down",
                "type": "Ethernet"
            },
            "Ethernet3/35": {
                "bandwidth": 1000000,
                "duplex": "auto",
                "macaddress": "fa16.3e88.4af6",
                "mode": "routed",
                "mtu": "1500",
                "speed": "auto-speed",
                "state": "down",
                "type": "Ethernet"
            },
            "Ethernet3/36": {
                "bandwidth": 1000000,
                "duplex": "auto",
                "macaddress": "fa16.3e88.4af6",
                "mode": "routed",
                "mtu": "1500",
                "speed": "auto-speed",
                "state": "down",
                "type": "Ethernet"
            },
            "Ethernet3/37": {
                "bandwidth": 1000000,
                "duplex": "auto",
                "macaddress": "fa16.3e88.4af6",
                "mode": "routed",
                "mtu": "1500",
                "speed": "auto-speed",
                "state": "down",
                "type": "Ethernet"
            },
            "Ethernet3/38": {
                "bandwidth": 1000000,
                "duplex": "auto",
                "macaddress": "fa16.3e88.4af6",
                "mode": "routed",
                "mtu": "1500",
                "speed": "auto-speed",
                "state": "down",
                "type": "Ethernet"
            },
            "Ethernet3/39": {
                "bandwidth": 1000000,
                "duplex": "auto",
                "macaddress": "fa16.3e88.4af6",
                "mode": "routed",
                "mtu": "1500",
                "speed": "auto-speed",
                "state": "down",
                "type": "Ethernet"
            },
            "Ethernet3/4": {
                "bandwidth": 1000000,
                "duplex": "auto",
                "macaddress": "fa16.3e88.4af6",
                "mode": "routed",
                "mtu": "1500",
                "speed": "auto-speed",
                "state": "down",
                "type": "Ethernet"
            },
            "Ethernet3/40": {
                "bandwidth": 1000000,
                "duplex": "auto",
                "macaddress": "fa16.3e88.4af6",
                "mode": "routed",
                "mtu": "1500",
                "speed": "auto-speed",
                "state": "down",
                "type": "Ethernet"
            },
            "Ethernet3/41": {
                "bandwidth": 1000000,
                "duplex": "auto",
                "macaddress": "fa16.3e88.4af6",
                "mode": "routed",
                "mtu": "1500",
                "speed": "auto-speed",
                "state": "down",
                "type": "Ethernet"
            },
            "Ethernet3/42": {
                "bandwidth": 1000000,
                "duplex": "auto",
                "macaddress": "fa16.3e88.4af6",
                "mode": "routed",
                "mtu": "1500",
                "speed": "auto-speed",
                "state": "down",
                "type": "Ethernet"
            },
            "Ethernet3/43": {
                "bandwidth": 1000000,
                "duplex": "auto",
                "macaddress": "fa16.3e88.4af6",
                "mode": "routed",
                "mtu": "1500",
                "speed": "auto-speed",
                "state": "down",
                "type": "Ethernet"
            },
            "Ethernet3/44": {
                "bandwidth": 1000000,
                "duplex": "auto",
                "macaddress": "fa16.3e88.4af6",
                "mode": "routed",
                "mtu": "1500",
                "speed": "auto-speed",
                "state": "down",
                "type": "Ethernet"
            },
            "Ethernet3/45": {
                "bandwidth": 1000000,
                "duplex": "auto",
                "macaddress": "fa16.3e88.4af6",
                "mode": "routed",
                "mtu": "1500",
                "speed": "auto-speed",
                "state": "down",
                "type": "Ethernet"
            },
            "Ethernet3/46": {
                "bandwidth": 1000000,
                "duplex": "auto",
                "macaddress": "fa16.3e88.4af6",
                "mode": "routed",
                "mtu": "1500",
                "speed": "auto-speed",
                "state": "down",
                "type": "Ethernet"
            },
            "Ethernet3/47": {
                "bandwidth": 1000000,
                "duplex": "auto",
                "macaddress": "fa16.3e88.4af6",
                "mode": "routed",
                "mtu": "1500",
                "speed": "auto-speed",
                "state": "down",
                "type": "Ethernet"
            },
            "Ethernet3/48": {
                "bandwidth": 1000000,
                "duplex": "auto",
                "macaddress": "fa16.3e88.4af6",
                "mode": "routed",
                "mtu": "1500",
                "speed": "auto-speed",
                "state": "down",
                "type": "Ethernet"
            },
            "Ethernet3/5": {
                "bandwidth": 1000000,
                "duplex": "auto",
                "macaddress": "fa16.3e88.4af6",
                "mode": "routed",
                "mtu": "1500",
                "speed": "auto-speed",
                "state": "down",
                "type": "Ethernet"
            },
            "Ethernet3/6": {
                "bandwidth": 1000000,
                "duplex": "auto",
                "macaddress": "fa16.3e88.4af6",
                "mode": "routed",
                "mtu": "1500",
                "speed": "auto-speed",
                "state": "down",
                "type": "Ethernet"
            },
            "Ethernet3/7": {
                "bandwidth": 1000000,
                "duplex": "auto",
                "macaddress": "fa16.3e88.4af6",
                "mode": "routed",
                "mtu": "1500",
                "speed": "auto-speed",
                "state": "down",
                "type": "Ethernet"
            },
            "Ethernet3/8": {
                "bandwidth": 1000000,
                "duplex": "auto",
                "macaddress": "fa16.3e88.4af6",
                "mode": "routed",
                "mtu": "1500",
                "speed": "auto-speed",
                "state": "down",
                "type": "Ethernet"
            },
            "Ethernet3/9": {
                "bandwidth": 1000000,
                "duplex": "auto",
                "macaddress": "fa16.3e88.4af6",
                "mode": "routed",
                "mtu": "1500",
                "speed": "auto-speed",
                "state": "down",
                "type": "Ethernet"
            },
            "Ethernet4/1": {
                "bandwidth": 1000000,
                "duplex": "auto",
                "macaddress": "0000.0000.002f",
                "mode": "access",
                "mtu": "1500",
                "speed": "auto-speed",
                "state": "down",
                "type": "Ethernet"
            },
            "Ethernet4/10": {
                "bandwidth": 1000000,
                "duplex": "auto",
                "macaddress": "0000.0000.0000",
                "mode": "access",
                "mtu": "1500",
                "speed": "auto-speed",
                "state": "down",
                "type": "Ethernet"
            },
            "Ethernet4/11": {
                "bandwidth": 1000000,
                "duplex": "auto",
                "macaddress": "0000.0000.0000",
                "mode": "access",
                "mtu": "1500",
                "speed": "auto-speed",
                "state": "down",
                "type": "Ethernet"
            },
            "Ethernet4/12": {
                "bandwidth": 1000000,
                "duplex": "auto",
                "macaddress": "0000.0000.0000",
                "mode": "access",
                "mtu": "1500",
                "speed": "auto-speed",
                "state": "down",
                "type": "Ethernet"
            },
            "Ethernet4/13": {
                "bandwidth": 1000000,
                "duplex": "auto",
                "macaddress": "0000.0000.0000",
                "mode": "access",
                "mtu": "1500",
                "speed": "auto-speed",
                "state": "down",
                "type": "Ethernet"
            },
            "Ethernet4/14": {
                "bandwidth": 1000000,
                "duplex": "auto",
                "macaddress": "0000.0000.0000",
                "mode": "access",
                "mtu": "1500",
                "speed": "auto-speed",
                "state": "down",
                "type": "Ethernet"
            },
            "Ethernet4/15": {
                "bandwidth": 1000000,
                "duplex": "auto",
                "macaddress": "0000.0000.0000",
                "mode": "access",
                "mtu": "1500",
                "speed": "auto-speed",
                "state": "down",
                "type": "Ethernet"
            },
            "Ethernet4/16": {
                "bandwidth": 1000000,
                "duplex": "auto",
                "macaddress": "0000.0000.0000",
                "mode": "access",
                "mtu": "1500",
                "speed": "auto-speed",
                "state": "down",
                "type": "Ethernet"
            },
            "Ethernet4/17": {
                "bandwidth": 1000000,
                "duplex": "auto",
                "macaddress": "0000.0000.0000",
                "mode": "access",
                "mtu": "1500",
                "speed": "auto-speed",
                "state": "down",
                "type": "Ethernet"
            },
            "Ethernet4/18": {
                "bandwidth": 1000000,
                "duplex": "auto",
                "macaddress": "0000.0000.0000",
                "mode": "access",
                "mtu": "1500",
                "speed": "auto-speed",
                "state": "down",
                "type": "Ethernet"
            },
            "Ethernet4/19": {
                "bandwidth": 1000000,
                "duplex": "auto",
                "macaddress": "0000.0000.0000",
                "mode": "access",
                "mtu": "1500",
                "speed": "auto-speed",
                "state": "down",
                "type": "Ethernet"
            },
            "Ethernet4/2": {
                "bandwidth": 1000000,
                "duplex": "auto",
                "macaddress": "0000.0000.002f",
                "mode": "access",
                "mtu": "1500",
                "speed": "auto-speed",
                "state": "down",
                "type": "Ethernet"
            },
            "Ethernet4/20": {
                "bandwidth": 1000000,
                "duplex": "auto",
                "macaddress": "0000.0000.0000",
                "mode": "access",
                "mtu": "1500",
                "speed": "auto-speed",
                "state": "down",
                "type": "Ethernet"
            },
            "Ethernet4/21": {
                "bandwidth": 1000000,
                "duplex": "auto",
                "macaddress": "0000.0000.0000",
                "mode": "access",
                "mtu": "1500",
                "speed": "auto-speed",
                "state": "down",
                "type": "Ethernet"
            },
            "Ethernet4/22": {
                "bandwidth": 1000000,
                "duplex": "auto",
                "macaddress": "0000.0000.0000",
                "mode": "access",
                "mtu": "1500",
                "speed": "auto-speed",
                "state": "down",
                "type": "Ethernet"
            },
            "Ethernet4/23": {
                "bandwidth": 1000000,
                "duplex": "auto",
                "macaddress": "0000.0000.0000",
                "mode": "access",
                "mtu": "1500",
                "speed": "auto-speed",
                "state": "down",
                "type": "Ethernet"
            },
            "Ethernet4/24": {
                "bandwidth": 1000000,
                "duplex": "auto",
                "macaddress": "0000.0000.0000",
                "mode": "access",
                "mtu": "1500",
                "speed": "auto-speed",
                "state": "down",
                "type": "Ethernet"
            },
            "Ethernet4/25": {
                "bandwidth": 1000000,
                "duplex": "auto",
                "macaddress": "0000.0000.0000",
                "mode": "access",
                "mtu": "1500",
                "speed": "auto-speed",
                "state": "down",
                "type": "Ethernet"
            },
            "Ethernet4/26": {
                "bandwidth": 1000000,
                "duplex": "auto",
                "macaddress": "0000.0000.0000",
                "mode": "access",
                "mtu": "1500",
                "speed": "auto-speed",
                "state": "down",
                "type": "Ethernet"
            },
            "Ethernet4/27": {
                "bandwidth": 1000000,
                "duplex": "auto",
                "macaddress": "0000.0000.0000",
                "mode": "access",
                "mtu": "1500",
                "speed": "auto-speed",
                "state": "down",
                "type": "Ethernet"
            },
            "Ethernet4/28": {
                "bandwidth": 1000000,
                "duplex": "auto",
                "macaddress": "0000.0000.0000",
                "mode": "access",
                "mtu": "1500",
                "speed": "auto-speed",
                "state": "down",
                "type": "Ethernet"
            },
            "Ethernet4/29": {
                "bandwidth": 1000000,
                "duplex": "auto",
                "macaddress": "0000.0000.0000",
                "mode": "access",
                "mtu": "1500",
                "speed": "auto-speed",
                "state": "down",
                "type": "Ethernet"
            },
            "Ethernet4/3": {
                "bandwidth": 1000000,
                "duplex": "auto",
                "macaddress": "0000.0000.002f",
                "mode": "access",
                "mtu": "1500",
                "speed": "auto-speed",
                "state": "down",
                "type": "Ethernet"
            },
            "Ethernet4/30": {
                "bandwidth": 1000000,
                "duplex": "auto",
                "macaddress": "0000.0000.0000",
                "mode": "access",
                "mtu": "1500",
                "speed": "auto-speed",
                "state": "down",
                "type": "Ethernet"
            },
            "Ethernet4/31": {
                "bandwidth": 1000000,
                "duplex": "auto",
                "macaddress": "0000.0000.0000",
                "mode": "access",
                "mtu": "1500",
                "speed": "auto-speed",
                "state": "down",
                "type": "Ethernet"
            },
            "Ethernet4/32": {
                "bandwidth": 1000000,
                "duplex": "auto",
                "macaddress": "0000.0000.0000",
                "mode": "access",
                "mtu": "1500",
                "speed": "auto-speed",
                "state": "down",
                "type": "Ethernet"
            },
            "Ethernet4/33": {
                "bandwidth": 1000000,
                "duplex": "auto",
                "macaddress": "0000.0000.0000",
                "mode": "access",
                "mtu": "1500",
                "speed": "auto-speed",
                "state": "down",
                "type": "Ethernet"
            },
            "Ethernet4/34": {
                "bandwidth": 1000000,
                "duplex": "auto",
                "macaddress": "0000.0000.0000",
                "mode": "access",
                "mtu": "1500",
                "speed": "auto-speed",
                "state": "down",
                "type": "Ethernet"
            },
            "Ethernet4/35": {
                "bandwidth": 1000000,
                "duplex": "auto",
                "macaddress": "0000.0000.0000",
                "mode": "access",
                "mtu": "1500",
                "speed": "auto-speed",
                "state": "down",
                "type": "Ethernet"
            },
            "Ethernet4/36": {
                "bandwidth": 1000000,
                "duplex": "auto",
                "macaddress": "0000.0000.0000",
                "mode": "access",
                "mtu": "1500",
                "speed": "auto-speed",
                "state": "down",
                "type": "Ethernet"
            },
            "Ethernet4/37": {
                "bandwidth": 1000000,
                "duplex": "auto",
                "macaddress": "0000.0000.0000",
                "mode": "access",
                "mtu": "1500",
                "speed": "auto-speed",
                "state": "down",
                "type": "Ethernet"
            },
            "Ethernet4/38": {
                "bandwidth": 1000000,
                "duplex": "auto",
                "macaddress": "0000.0000.0000",
                "mode": "access",
                "mtu": "1500",
                "speed": "auto-speed",
                "state": "down",
                "type": "Ethernet"
            },
            "Ethernet4/39": {
                "bandwidth": 1000000,
                "duplex": "auto",
                "macaddress": "0000.0000.0000",
                "mode": "access",
                "mtu": "1500",
                "speed": "auto-speed",
                "state": "down",
                "type": "Ethernet"
            },
            "Ethernet4/4": {
                "bandwidth": 1000000,
                "duplex": "auto",
                "macaddress": "0000.0000.0000",
                "mode": "access",
                "mtu": "1500",
                "speed": "auto-speed",
                "state": "down",
                "type": "Ethernet"
            },
            "Ethernet4/40": {
                "bandwidth": 1000000,
                "duplex": "auto",
                "macaddress": "0000.0000.0000",
                "mode": "access",
                "mtu": "1500",
                "speed": "auto-speed",
                "state": "down",
                "type": "Ethernet"
            },
            "Ethernet4/41": {
                "bandwidth": 1000000,
                "duplex": "auto",
                "macaddress": "0000.0000.0000",
                "mode": "access",
                "mtu": "1500",
                "speed": "auto-speed",
                "state": "down",
                "type": "Ethernet"
            },
            "Ethernet4/42": {
                "bandwidth": 1000000,
                "duplex": "auto",
                "macaddress": "0000.0000.0000",
                "mode": "access",
                "mtu": "1500",
                "speed": "auto-speed",
                "state": "down",
                "type": "Ethernet"
            },
            "Ethernet4/43": {
                "bandwidth": 1000000,
                "duplex": "auto",
                "macaddress": "0000.0000.0000",
                "mode": "access",
                "mtu": "1500",
                "speed": "auto-speed",
                "state": "down",
                "type": "Ethernet"
            },
            "Ethernet4/44": {
                "bandwidth": 1000000,
                "duplex": "auto",
                "macaddress": "0000.0000.0000",
                "mode": "access",
                "mtu": "1500",
                "speed": "auto-speed",
                "state": "down",
                "type": "Ethernet"
            },
            "Ethernet4/45": {
                "bandwidth": 1000000,
                "duplex": "auto",
                "macaddress": "0000.0000.0000",
                "mode": "access",
                "mtu": "1500",
                "speed": "auto-speed",
                "state": "down",
                "type": "Ethernet"
            },
            "Ethernet4/46": {
                "bandwidth": 1000000,
                "duplex": "auto",
                "macaddress": "0000.0000.0000",
                "mode": "access",
                "mtu": "1500",
                "speed": "auto-speed",
                "state": "down",
                "type": "Ethernet"
            },
            "Ethernet4/47": {
                "bandwidth": 1000000,
                "duplex": "auto",
                "macaddress": "0000.0000.0000",
                "mode": "access",
                "mtu": "1500",
                "speed": "auto-speed",
                "state": "down",
                "type": "Ethernet"
            },
            "Ethernet4/48": {
                "bandwidth": 1000000,
                "duplex": "auto",
                "macaddress": "0000.0000.0000",
                "mode": "access",
                "mtu": "1500",
                "speed": "auto-speed",
                "state": "down",
                "type": "Ethernet"
            },
            "Ethernet4/5": {
                "bandwidth": 1000000,
                "duplex": "auto",
                "macaddress": "0000.0000.0000",
                "mode": "access",
                "mtu": "1500",
                "speed": "auto-speed",
                "state": "down",
                "type": "Ethernet"
            },
            "Ethernet4/6": {
                "bandwidth": 1000000,
                "duplex": "auto",
                "macaddress": "0000.0000.0000",
                "mode": "access",
                "mtu": "1500",
                "speed": "auto-speed",
                "state": "down",
                "type": "Ethernet"
            },
            "Ethernet4/7": {
                "bandwidth": 1000000,
                "duplex": "auto",
                "macaddress": "0000.0000.0000",
                "mode": "access",
                "mtu": "1500",
                "speed": "auto-speed",
                "state": "down",
                "type": "Ethernet"
            },
            "Ethernet4/8": {
                "bandwidth": 1000000,
                "duplex": "auto",
                "macaddress": "0000.0000.0000",
                "mode": "access",
                "mtu": "1500",
                "speed": "auto-speed",
                "state": "down",
                "type": "Ethernet"
            },
            "Ethernet4/9": {
                "bandwidth": 1000000,
                "duplex": "auto",
                "macaddress": "0000.0000.0000",
                "mode": "access",
                "mtu": "1500",
                "speed": "auto-speed",
                "state": "down",
                "type": "Ethernet"
            },
            "mgmt0": {
                "bandwidth": 1000000,
                "duplex": "full",
                "ipv4": {
                    "address": "172.16.1.13",
                    "masklen": 24
                },
                "macaddress": "5e00.0003.0000",
                "mode": "routed",
                "mtu": "1500",
                "speed": "1000 Mb/s",
                "state": "up",
                "type": "Ethernet"
            }
        },
        "ansible_net_memfree_mb": 995,
        "ansible_net_memtotal_mb": 2992,
        "ansible_net_model": "NX-OSv Chassis",
        "ansible_net_neighbors": {
            "mgmt0": [
                {
                    "port": "mgmt0",
                    "sysname": "switch(TB00070000B)"
                }
            ]
        },
        "ansible_net_serialnum": "TM00030000B",
        "ansible_net_version": "7.3(0)D1(1)",
        "fan_info": [
            {
                "hw_ver": "0.0",
                "model": null,
                "name": "ChassisFan1",
                "status": "Ok"
            },
            {
                "hw_ver": "0.0",
                "model": null,
                "name": "ChassisFan2",
                "status": "None"
            },
            {
                "hw_ver": "--",
                "model": "--",
                "name": "Fan_in_PS1",
                "status": "Ok"
            },
            {
                "hw_ver": "--",
                "model": "--",
                "name": "Fan_in_PS2",
                "status": "Failure"
            }
        ],
        "hostname": "switch",
        "interfaces_list": [
            "mgmt0",
            "Ethernet2/1",
            "Ethernet2/2",
            "Ethernet2/3",
            "Ethernet2/4",
            "Ethernet2/5",
            "Ethernet2/6",
            "Ethernet2/7",
            "Ethernet2/8",
            "Ethernet2/9",
            "Ethernet2/10",
            "Ethernet2/11",
            "Ethernet2/12",
            "Ethernet2/13",
            "Ethernet2/14",
            "Ethernet2/15",
            "Ethernet2/16",
            "Ethernet2/17",
            "Ethernet2/18",
            "Ethernet2/19",
            "Ethernet2/20",
            "Ethernet2/21",
            "Ethernet2/22",
            "Ethernet2/23",
            "Ethernet2/24",
            "Ethernet2/25",
            "Ethernet2/26",
            "Ethernet2/27",
            "Ethernet2/28",
            "Ethernet2/29",
            "Ethernet2/30",
            "Ethernet2/31",
            "Ethernet2/32",
            "Ethernet2/33",
            "Ethernet2/34",
            "Ethernet2/35",
            "Ethernet2/36",
            "Ethernet2/37",
            "Ethernet2/38",
            "Ethernet2/39",
            "Ethernet2/40",
            "Ethernet2/41",
            "Ethernet2/42",
            "Ethernet2/43",
            "Ethernet2/44",
            "Ethernet2/45",
            "Ethernet2/46",
            "Ethernet2/47",
            "Ethernet2/48",
            "Ethernet3/1",
            "Ethernet3/2",
            "Ethernet3/3",
            "Ethernet3/4",
            "Ethernet3/5",
            "Ethernet3/6",
            "Ethernet3/7",
            "Ethernet3/8",
            "Ethernet3/9",
            "Ethernet3/10",
            "Ethernet3/11",
            "Ethernet3/12",
            "Ethernet3/13",
            "Ethernet3/14",
            "Ethernet3/15",
            "Ethernet3/16",
            "Ethernet3/17",
            "Ethernet3/18",
            "Ethernet3/19",
            "Ethernet3/20",
            "Ethernet3/21",
            "Ethernet3/22",
            "Ethernet3/23",
            "Ethernet3/24",
            "Ethernet3/25",
            "Ethernet3/26",
            "Ethernet3/27",
            "Ethernet3/28",
            "Ethernet3/29",
            "Ethernet3/30",
            "Ethernet3/31",
            "Ethernet3/32",
            "Ethernet3/33",
            "Ethernet3/34",
            "Ethernet3/35",
            "Ethernet3/36",
            "Ethernet3/37",
            "Ethernet3/38",
            "Ethernet3/39",
            "Ethernet3/40",
            "Ethernet3/41",
            "Ethernet3/42",
            "Ethernet3/43",
            "Ethernet3/44",
            "Ethernet3/45",
            "Ethernet3/46",
            "Ethernet3/47",
            "Ethernet3/48",
            "Ethernet4/1",
            "Ethernet4/2",
            "Ethernet4/3",
            "Ethernet4/4",
            "Ethernet4/5",
            "Ethernet4/6",
            "Ethernet4/7",
            "Ethernet4/8",
            "Ethernet4/9",
            "Ethernet4/10",
            "Ethernet4/11",
            "Ethernet4/12",
            "Ethernet4/13",
            "Ethernet4/14",
            "Ethernet4/15",
            "Ethernet4/16",
            "Ethernet4/17",
            "Ethernet4/18",
            "Ethernet4/19",
            "Ethernet4/20",
            "Ethernet4/21",
            "Ethernet4/22",
            "Ethernet4/23",
            "Ethernet4/24",
            "Ethernet4/25",
            "Ethernet4/26",
            "Ethernet4/27",
            "Ethernet4/28",
            "Ethernet4/29",
            "Ethernet4/30",
            "Ethernet4/31",
            "Ethernet4/32",
            "Ethernet4/33",
            "Ethernet4/34",
            "Ethernet4/35",
            "Ethernet4/36",
            "Ethernet4/37",
            "Ethernet4/38",
            "Ethernet4/39",
            "Ethernet4/40",
            "Ethernet4/41",
            "Ethernet4/42",
            "Ethernet4/43",
            "Ethernet4/44",
            "Ethernet4/45",
            "Ethernet4/46",
            "Ethernet4/47",
            "Ethernet4/48"
        ],
        "module": [
            {
                "model": "N7K-SUP1",
                "ports": 0,
                "status": "active *",
                "type": "NX-OSv Supervisor Module"
            },
            {
                "model": "N7K-F248XP-25",
                "ports": 48,
                "status": "ok",
                "type": "NX-OSv Ethernet Module"
            },
            {
                "model": "N7K-F248XP-25",
                "ports": 48,
                "status": "ok",
                "type": "NX-OSv Ethernet Module"
            },
            {
                "model": "N7K-F248XP-25",
                "ports": 48,
                "status": "ok",
                "type": "NX-OSv Ethernet Module"
            }
        ],
        "os": "7.3(0)D1(1)",
        "platform": "NX-OSv Chassis",
        "power_supply_info": [
            {
                "amps": "77.96",
                "model": "DS-CAC-845W",
                "number": 1,
                "status": "Ok",
                "watts": "3274.32"
            },
            {
                "amps": "0.00",
                "model": "------------",
                "number": 2,
                "status": "Absent",
                "watts": "0.00"
            }
        ],
        "vlan_list": [
            1
        ]
    },
    "changed": false,
    "failed": false
}