{
    "ansible_facts": {
        "ansible_net_all_ipv4_addresses": [
            "172.16.1.15",
            "10.0.1.13",
            "10.0.2.13",
            "192.168.0.18",
            "192.168.0.1"
        ],
        "ansible_net_all_ipv6_addresses": [],
        "ansible_net_config": "!Command: show running-config\n!Time: Tue Apr 30 13:37:56 2019\n\nversion 7.3(0)D1(1)\npower redundancy-mode combined force\nlicense grace-period\n\nhostname nx-osv-6\nvdc nx-osv-6 id 1\n  limit-resource module-type m1 m1xl m2xl f2e \n  allocate interface Ethernet2/1-48\n  allocate interface Ethernet3/1-48\n  allocate interface Ethernet4/1-48\n  limit-resource vlan minimum 16 maximum 4094\n  limit-resource vrf minimum 2 maximum 4096\n  limit-resource port-channel minimum 0 maximum 768\n  limit-resource u4route-mem minimum 96 maximum 96\n  limit-resource u6route-mem minimum 24 maximum 24\n  limit-resource m4route-mem minimum 58 maximum 58\n  limit-resource m6route-mem minimum 8 maximum 8\n\nfeature telnet\nfeature scp-server\nnv overlay evpn\nfeature ospf\nfeature bgp\nfeature ospfv3\nfeature pim\nfeature msdp\nfeature eigrp\nfeature private-vlan\nfeature interface-vlan\nfeature vn-segment-vlan-based\nfeature hsrp\nfeature lldp\nfeature bfd\nfeature nv overlay\n\nfeature ngoam\n\nusername admin password 5 $1$KuOSBsvW$Cy0TSD..gEBGBPjzpDgf51  role network-admin\nusername adminbackup password 5 !  role network-operator\nusername adminbackup passphrase  lifetime 99999 warntime 14 gracetime 3\nusername cisco password 5 $1$Nk7ZkwH0$fyiRmMMfIheqE3BqvcL0C1  role network-operator\nusername cisco role network-admin\nusername cisco passphrase  lifetime 99999 warntime 14 gracetime 3\nusername lab password 5 $1$buoy/oqy$.EXQz8rCn72ii8qtdldj00  role network-admin\nusername lab passphrase  lifetime 99999 warntime 14 gracetime 3\nusername netadmin password 5 $5$emOkY3RY$cuBIqbRTRyVwfmOhcL4UbMF95r2CQKvQ8rQjdFy9wx.  role network-admin\nusername netadmin sshkey ssh-rsa AAAAB3NzaC1yc2EAAAADAQABAAABAQDA8zh97flbXBI35NiYRC0A5EcFGHEJTf59o+wGKUhn2FN6SHdLBmcbsyBbSBSPgcC92UIaxls1F6xc4T2dU+be5MF3r7wGcYfqxGOeiHQbwbc0BDvYxu36uznzvbYvMTx2f7WdKi4N0ngpmLPPabWQQi+nwZCDO8MfyQ3edPY7KMGN5u1xXh7ni4sj+Kt8E/c8CgI+Y98UUvz77yiFByJoAOVhqije+E/e+jeVRiWsCXEy70pqm9OxW3zo3GtYi7ydFL8zt8pckbJ1aAKs5wSSDuwIr4Gfu4E5PL+DpB0/atlYdqGsOcQR3gMgOwxDnO/n4MrjPreqY8p8KbbeCuql netadmin@ansible.insiel.it\n\nusername netadmin passphrase  lifetime 99999 warntime 14 gracetime 3\nusername netoperator password 5 $5$emOkY3RY$cuBIqbRTRyVwfmOhcL4UbMF95r2CQKvQ8rQjdFy9wx.  role network-operator\nusername netoperator passphrase  lifetime 99999 warntime 14 gracetime 3\nno password strength-check\nno ip domain-lookup\nradius-server timeout 1\nradius-server retransmit 2\nradius-server deadtime 5\nradius-server host 172.16.1.1 key 7 \"puwjurzy\" authentication accounting \nradius-server host 172.16.1.2 key 7 \"puwjurzy\" authentication accounting \naaa group server radius MYRADIUS \n    server 172.16.1.1 \n    server 172.16.1.2 \n    use-vrf management\n    source-interface mgmt0\nvlan dot1Q tag native\nsystem default switchport\nsystem jumbomtu 0\nno logging event trunk-status enable\nerrdisable recovery cause link-flap\nerrdisable recovery cause udld\nerrdisable recovery cause loopback\ncopp profile strict\nsnmp-server contact admin@net-automation-lab.local\nsnmp-server location 170 West Tasman Drive - San Jose, CA 95134-170 USA\nsnmp-server source-interface traps mgmt0\nsnmp-server source-interface informs mgmt0\nsnmp-server user lab network-admin auth md5 0x5ceb414591539ee35159fca86fdfa101 priv 0x5ceb414591539ee35159fca86fdfa101 localizedkey\nsnmp-server user admin network-admin auth md5 0x328945d53e05e8e7207f8c20b142f0b7 priv 0x328945d53e05e8e7207f8c20b142f0b7 localizedkey\nsnmp-server user cisco network-admin auth md5 0x55b3c64a53fb95518e75358ee75e82e9 priv 0x55b3c64a53fb95518e75358ee75e82e9 localizedkey\nsnmp-server user cisco network-operator\nsnmp-server user admin auth md5 0x328945d53e05e8e7207f8c20b142f0b7 priv 0x328945d53e05e8e7207f8c20b142f0b7 localizedkey engineID 128:0:0:9:3:0:0:0:0:0:0\nrmon event 1 log trap public description FATAL(1) owner PMON@FATAL\nrmon event 2 log trap public description CRITICAL(2) owner PMON@CRITICAL\nrmon event 3 log trap public description ERROR(3) owner PMON@ERROR\nrmon event 4 log trap public description WARNING(4) owner PMON@WARNING\nrmon event 5 log trap public description INFORMATION(5) owner PMON@INFO\nsnmp-server enable traps bgp\nsnmp-server enable traps link\nsnmp-server enable traps hsrp state-change\nsnmp-server enable traps sysmgr cseFailSwCoreNotifyExtended\nsnmp-server enable traps config ccmCLIRunningConfigChanged\nsnmp-server enable traps snmp authentication\nsnmp-server enable traps system Clock-change-notification\nsnmp-server community myROcommunity group network-operator\nsnmp-server community myRWcommunity group network-operator\nntp server 172.16.1.1 use-vrf management\nntp server 172.16.1.2 use-vrf management\nntp source-interface  mgmt0\naaa authentication login default group MYRADIUS \naaa accounting default group MYRADIUS \nradius-server directed-request \n\nip pim rp-address 192.168.0.2 group-list 239.0.0.0/8\nip pim ssm range 232.0.0.0/8\nvlan 1,1001,3801,3803\nvlan 1001\n  name l3-CUSTOMER-02\nvlan 3801\n  name L2-CUSTOMER-01\n  vn-segment 13801\nvlan 3803\n  name L3-CUSTOMER-02\n  vn-segment 13803\n\nspanning-tree mode mst\nvrf context CUSTOMER-02\n  ip pim ssm range 232.0.0.0/8\n  rd 1:1\n  address-family ipv4 unicast\n    route-target import 1:1\n    route-target import 1:1 evpn\n    route-target export 1:1\n    route-target export 1:1 evpn\nvrf context management\n  ip route 0.0.0.0/0 172.16.1.1\nhardware forwarding unicast trace\n\n\ninterface mgmt0\n  description OOB Management\n  duplex full\n  vrf member management\n  ip address 172.16.1.15/24\n\ninterface Vlan1\n\ninterface Vlan1001\n  description l3-CUSTOMER-02\n  no shutdown\n  mtu 9216\n  vrf member CUSTOMER-02\n  no ip redirects\n  ip forward\n  no ipv6 redirects\n\ninterface Vlan3803\n  description CUSTOMER-02 - VLAN\n  no shutdown\n  mtu 9100\n  vrf member CUSTOMER-02\n  ip address 192.168.0.1/24\n\ninterface nve1\n  no shutdown\n  source-interface loopback0\n  host-reachability protocol bgp\n  member vni 13803\n    mcast-group 239.1.0.1\n\ninterface Ethernet2/1\n  description Link to Spine-1\n  no switchport\n  mtu 9216\n  mac-address fa16.3e00.0017\n  ip address 10.0.1.13/31\n  ip ospf network point-to-point\n  no ip ospf passive-interface\n  ip router ospf underlay area 0.0.0.1\n  ip pim sparse-mode\n  no shutdown\n\ninterface Ethernet2/2\n  description Link to Spine-2\n  no switchport\n  mtu 9216\n  mac-address fa16.3e00.0018\n  ip address 10.0.2.13/31\n  ip ospf network point-to-point\n  no ip ospf passive-interface\n  ip router ospf underlay area 0.0.0.1\n  ip pim sparse-mode\n  no shutdown\n\ninterface Ethernet2/3\n  description ESX1\n  no switchport\n  spanning-tree port type edge\n  spanning-tree bpduguard enable\n  spanning-tree guard root\n  mtu 9216\n  mac-address fa16.3e00.0019\n  no shutdown\n\ninterface Ethernet2/4\n  description Backup\n  no switchport\n  spanning-tree port type edge\n  spanning-tree bpduguard enable\n  spanning-tree guard root\n  mtu 9216\n  mac-address 0000.0000.002f\n  no shutdown\n\ninterface Ethernet2/5\n  shutdown\n  no switchport\n  mac-address 0000.0000.002f\n\ninterface Ethernet2/6\n  shutdown\n  no switchport\n  mac-address 0000.0000.002f\n\ninterface Ethernet2/7\n  shutdown\n  no switchport\n  mac-address 0000.0000.002f\n\ninterface Ethernet2/8\n  shutdown\n  no switchport\n  mac-address 0000.0000.002f\n\ninterface Ethernet2/9\n  shutdown\n  no switchport\n  mac-address 0000.0000.002f\n\ninterface Ethernet2/10\n  shutdown\n  no switchport\n  mac-address 0000.0000.002f\n\ninterface Ethernet2/11\n  shutdown\n  no switchport\n  mac-address 0000.0000.002f\n\ninterface Ethernet2/12\n  shutdown\n  no switchport\n  mac-address 0000.0000.002f\n\ninterface Ethernet2/13\n  shutdown\n  no switchport\n  mac-address 0000.0000.002f\n\ninterface Ethernet2/14\n  shutdown\n  no switchport\n  mac-address 0000.0000.002f\n\ninterface Ethernet2/15\n  shutdown\n  no switchport\n  mac-address 0000.0000.002f\n\ninterface Ethernet2/16\n  shutdown\n  no switchport\n  mac-address 0000.0000.002f\n\ninterface Ethernet2/17\n  shutdown\n  no switchport\n  mac-address 0000.0000.002f\n\ninterface Ethernet2/18\n  shutdown\n  no switchport\n  mac-address 0000.0000.002f\n\ninterface Ethernet2/19\n  shutdown\n  no switchport\n  mac-address 0000.0000.002f\n\ninterface Ethernet2/20\n  shutdown\n  no switchport\n  mac-address 0000.0000.002f\n\ninterface Ethernet2/21\n  shutdown\n  no switchport\n  mac-address 0000.0000.002f\n\ninterface Ethernet2/22\n  shutdown\n  no switchport\n  mac-address 0000.0000.002f\n\ninterface Ethernet2/23\n  shutdown\n  no switchport\n  mac-address 0000.0000.002f\n\ninterface Ethernet2/24\n  shutdown\n  no switchport\n  mac-address 0000.0000.002f\n\ninterface Ethernet2/25\n  shutdown\n  no switchport\n  mac-address 0000.0000.002f\n\ninterface Ethernet2/26\n  shutdown\n  no switchport\n  mac-address 0000.0000.002f\n\ninterface Ethernet2/27\n  shutdown\n  no switchport\n  mac-address 0000.0000.002f\n\ninterface Ethernet2/28\n  shutdown\n  no switchport\n  mac-address 0000.0000.002f\n\ninterface Ethernet2/29\n  shutdown\n  no switchport\n  mac-address 0000.0000.002f\n\ninterface Ethernet2/30\n  shutdown\n  no switchport\n  mac-address 0000.0000.002f\n\ninterface Ethernet2/31\n  shutdown\n  no switchport\n  mac-address 0000.0000.002f\n\ninterface Ethernet2/32\n  shutdown\n  no switchport\n  mac-address 0000.0000.002f\n\ninterface Ethernet2/33\n  shutdown\n  no switchport\n  mac-address 0000.0000.002f\n\ninterface Ethernet2/34\n  shutdown\n  no switchport\n  mac-address 0000.0000.002f\n\ninterface Ethernet2/35\n  shutdown\n  no switchport\n  mac-address 0000.0000.002f\n\ninterface Ethernet2/36\n  shutdown\n  no switchport\n  mac-address 0000.0000.002f\n\ninterface Ethernet2/37\n  shutdown\n  no switchport\n  mac-address 0000.0000.002f\n\ninterface Ethernet2/38\n  shutdown\n  no switchport\n  mac-address 0000.0000.002f\n\ninterface Ethernet2/39\n  shutdown\n  no switchport\n  mac-address 0000.0000.002f\n\ninterface Ethernet2/40\n  shutdown\n  no switchport\n  mac-address 0000.0000.002f\n\ninterface Ethernet2/41\n  shutdown\n  no switchport\n  mac-address 0000.0000.002f\n\ninterface Ethernet2/42\n  shutdown\n  no switchport\n  mac-address 0000.0000.002f\n\ninterface Ethernet2/43\n  shutdown\n  no switchport\n  mac-address 0000.0000.002f\n\ninterface Ethernet2/44\n  shutdown\n  no switchport\n  mac-address 0000.0000.002f\n\ninterface Ethernet2/45\n  shutdown\n  no switchport\n  mac-address 0000.0000.002f\n\ninterface Ethernet2/46\n  shutdown\n  no switchport\n  mac-address 0000.0000.002f\n\ninterface Ethernet2/47\n  shutdown\n  no switchport\n  mac-address 0000.0000.002f\n\ninterface Ethernet2/48\n  shutdown\n  no switchport\n  mac-address 0000.0000.002f\n\ninterface Ethernet3/1\n  shutdown\n  no switchport\n  mac-address 0000.0000.002f\n\ninterface Ethernet3/2\n  shutdown\n  no switchport\n  mac-address 0000.0000.002f\n\ninterface Ethernet3/3\n  shutdown\n  no switchport\n  mac-address 0000.0000.002f\n\ninterface Ethernet3/4\n  shutdown\n  no switchport\n  mac-address 0000.0000.002f\n\ninterface Ethernet3/5\n  shutdown\n  no switchport\n  mac-address 0000.0000.002f\n\ninterface Ethernet3/6\n  shutdown\n  no switchport\n  mac-address 0000.0000.002f\n\ninterface Ethernet3/7\n  shutdown\n  no switchport\n  mac-address 0000.0000.002f\n\ninterface Ethernet3/8\n  shutdown\n  no switchport\n  mac-address 0000.0000.002f\n\ninterface Ethernet3/9\n  shutdown\n  no switchport\n  mac-address 0000.0000.002f\n\ninterface Ethernet3/10\n  shutdown\n  no switchport\n  mac-address 0000.0000.002f\n\ninterface Ethernet3/11\n  shutdown\n  no switchport\n  mac-address 0000.0000.002f\n\ninterface Ethernet3/12\n  shutdown\n  no switchport\n  mac-address 0000.0000.002f\n\ninterface Ethernet3/13\n  shutdown\n  no switchport\n  mac-address 0000.0000.002f\n\ninterface Ethernet3/14\n  shutdown\n  no switchport\n  mac-address 0000.0000.002f\n\ninterface Ethernet3/15\n  shutdown\n  no switchport\n  mac-address 0000.0000.002f\n\ninterface Ethernet3/16\n  shutdown\n  no switchport\n  mac-address 0000.0000.002f\n\ninterface Ethernet3/17\n  shutdown\n  no switchport\n  mac-address 0000.0000.002f\n\ninterface Ethernet3/18\n  shutdown\n  no switchport\n  mac-address 0000.0000.002f\n\ninterface Ethernet3/19\n  shutdown\n  no switchport\n  mac-address 0000.0000.002f\n\ninterface Ethernet3/20\n  shutdown\n  no switchport\n  mac-address 0000.0000.002f\n\ninterface Ethernet3/21\n  shutdown\n  no switchport\n  mac-address 0000.0000.002f\n\ninterface Ethernet3/22\n  shutdown\n  no switchport\n  mac-address 0000.0000.002f\n\ninterface Ethernet3/23\n  shutdown\n  no switchport\n  mac-address 0000.0000.002f\n\ninterface Ethernet3/24\n  shutdown\n  no switchport\n  mac-address 0000.0000.002f\n\ninterface Ethernet3/25\n  shutdown\n  no switchport\n  mac-address 0000.0000.002f\n\ninterface Ethernet3/26\n  shutdown\n  no switchport\n  mac-address 0000.0000.002f\n\ninterface Ethernet3/27\n  shutdown\n  no switchport\n  mac-address 0000.0000.002f\n\ninterface Ethernet3/28\n  shutdown\n  no switchport\n  mac-address 0000.0000.002f\n\ninterface Ethernet3/29\n  shutdown\n  no switchport\n  mac-address 0000.0000.002f\n\ninterface Ethernet3/30\n  shutdown\n  no switchport\n  mac-address 0000.0000.002f\n\ninterface Ethernet3/31\n  shutdown\n  no switchport\n  mac-address 0000.0000.002f\n\ninterface Ethernet3/32\n  shutdown\n  no switchport\n  mac-address 0000.0000.002f\n\ninterface Ethernet3/33\n  shutdown\n  no switchport\n  mac-address 0000.0000.002f\n\ninterface Ethernet3/34\n  shutdown\n  no switchport\n  mac-address 0000.0000.002f\n\ninterface Ethernet3/35\n  shutdown\n  no switchport\n  mac-address 0000.0000.002f\n\ninterface Ethernet3/36\n  shutdown\n  no switchport\n  mac-address 0000.0000.002f\n\ninterface Ethernet3/37\n  shutdown\n  no switchport\n  mac-address 0000.0000.002f\n\ninterface Ethernet3/38\n  shutdown\n  no switchport\n  mac-address 0000.0000.002f\n\ninterface Ethernet3/39\n  shutdown\n  no switchport\n  mac-address 0000.0000.002f\n\ninterface Ethernet3/40\n  shutdown\n  no switchport\n  mac-address 0000.0000.002f\n\ninterface Ethernet3/41\n  shutdown\n  no switchport\n  mac-address 0000.0000.002f\n\ninterface Ethernet3/42\n  shutdown\n  no switchport\n  mac-address 0000.0000.002f\n\ninterface Ethernet3/43\n  shutdown\n  no switchport\n  mac-address 0000.0000.002f\n\ninterface Ethernet3/44\n  shutdown\n  no switchport\n  mac-address 0000.0000.002f\n\ninterface Ethernet3/45\n  shutdown\n  no switchport\n  mac-address 0000.0000.002f\n\ninterface Ethernet3/46\n  shutdown\n  no switchport\n  mac-address 0000.0000.002f\n\ninterface Ethernet3/47\n  shutdown\n  no switchport\n  mac-address 0000.0000.002f\n\ninterface Ethernet3/48\n  shutdown\n  no switchport\n  mac-address 0000.0000.002f\n\ninterface Ethernet4/1\n  shutdown\n  no switchport\n  mac-address 0000.0000.002f\n\ninterface Ethernet4/2\n  shutdown\n  no switchport\n  mac-address 0000.0000.002f\n\ninterface Ethernet4/3\n  shutdown\n  no switchport\n  mac-address 0000.0000.002f\n\ninterface Ethernet4/4\n  shutdown\n  no switchport\n  mac-address 0000.0000.002f\n\ninterface Ethernet4/5\n  shutdown\n  no switchport\n  mac-address 0000.0000.002f\n\ninterface Ethernet4/6\n  shutdown\n  no switchport\n  mac-address 0000.0000.002f\n\ninterface Ethernet4/7\n  shutdown\n  no switchport\n  mac-address 0000.0000.002f\n\ninterface Ethernet4/8\n  shutdown\n  no switchport\n  mac-address 0000.0000.002f\n\ninterface Ethernet4/9\n  shutdown\n  no switchport\n  mac-address 0000.0000.002f\n\ninterface Ethernet4/10\n  shutdown\n  no switchport\n  mac-address 0000.0000.002f\n\ninterface Ethernet4/11\n  shutdown\n  no switchport\n  mac-address 0000.0000.002f\n\ninterface Ethernet4/12\n  shutdown\n  no switchport\n  mac-address 0000.0000.002f\n\ninterface Ethernet4/13\n  shutdown\n  no switchport\n  mac-address 0000.0000.002f\n\ninterface Ethernet4/14\n  shutdown\n  no switchport\n  mac-address 0000.0000.002f\n\ninterface Ethernet4/15\n  shutdown\n  no switchport\n  mac-address 0000.0000.002f\n\ninterface Ethernet4/16\n  shutdown\n  no switchport\n  mac-address 0000.0000.002f\n\ninterface Ethernet4/17\n  shutdown\n  no switchport\n  mac-address 0000.0000.002f\n\ninterface Ethernet4/18\n  shutdown\n  no switchport\n  mac-address 0000.0000.002f\n\ninterface Ethernet4/19\n  shutdown\n  no switchport\n  mac-address 0000.0000.002f\n\ninterface Ethernet4/20\n  shutdown\n  no switchport\n  mac-address 0000.0000.002f\n\ninterface Ethernet4/21\n  shutdown\n  no switchport\n  mac-address 0000.0000.002f\n\ninterface Ethernet4/22\n  shutdown\n  no switchport\n  mac-address 0000.0000.002f\n\ninterface Ethernet4/23\n  shutdown\n  no switchport\n  mac-address 0000.0000.002f\n\ninterface Ethernet4/24\n  shutdown\n  no switchport\n  mac-address 0000.0000.002f\n\ninterface Ethernet4/25\n  shutdown\n  no switchport\n  mac-address 0000.0000.002f\n\ninterface Ethernet4/26\n  shutdown\n  no switchport\n  mac-address 0000.0000.002f\n\ninterface Ethernet4/27\n  shutdown\n  no switchport\n  mac-address 0000.0000.002f\n\ninterface Ethernet4/28\n  shutdown\n  no switchport\n  mac-address 0000.0000.002f\n\ninterface Ethernet4/29\n  shutdown\n  no switchport\n  mac-address 0000.0000.002f\n\ninterface Ethernet4/30\n  shutdown\n  no switchport\n  mac-address 0000.0000.002f\n\ninterface Ethernet4/31\n  shutdown\n  no switchport\n  mac-address 0000.0000.002f\n\ninterface Ethernet4/32\n  shutdown\n  no switchport\n  mac-address 0000.0000.002f\n\ninterface Ethernet4/33\n  shutdown\n  no switchport\n  mac-address 0000.0000.002f\n\ninterface Ethernet4/34\n  shutdown\n  no switchport\n  mac-address 0000.0000.002f\n\ninterface Ethernet4/35\n  shutdown\n  no switchport\n  mac-address 0000.0000.002f\n\ninterface Ethernet4/36\n  shutdown\n  no switchport\n  mac-address 0000.0000.002f\n\ninterface Ethernet4/37\n  shutdown\n  no switchport\n  mac-address 0000.0000.002f\n\ninterface Ethernet4/38\n  shutdown\n  no switchport\n  mac-address 0000.0000.002f\n\ninterface Ethernet4/39\n  shutdown\n  no switchport\n  mac-address 0000.0000.002f\n\ninterface Ethernet4/40\n  shutdown\n  no switchport\n  mac-address 0000.0000.002f\n\ninterface Ethernet4/41\n  shutdown\n  no switchport\n  mac-address 0000.0000.002f\n\ninterface Ethernet4/42\n  shutdown\n  no switchport\n  mac-address 0000.0000.002f\n\ninterface Ethernet4/43\n  shutdown\n  no switchport\n  mac-address 0000.0000.002f\n\ninterface Ethernet4/44\n  shutdown\n  no switchport\n  mac-address 0000.0000.002f\n\ninterface Ethernet4/45\n  shutdown\n  no switchport\n  mac-address 0000.0000.002f\n\ninterface Ethernet4/46\n  shutdown\n  no switchport\n  mac-address 0000.0000.002f\n\ninterface Ethernet4/47\n  shutdown\n  no switchport\n  mac-address 0000.0000.002f\n\ninterface Ethernet4/48\n  shutdown\n  no switchport\n  mac-address 0000.0000.002f\n\ninterface loopback0\n  description Loopback\n  ip address 192.168.0.18/24\n  ip router ospf underlay area 0.0.0.1\n  ip pim sparse-mode\nclock timezone CET 1 0\ncli alias name wr copy run start\ncli alias name vxlanrt show bgp l2vpn evpn\ncli alias name ipint show ip interf brief vrf all\ncli alias name underlay show ip ospf underlay\ncli alias name overlay show ip ospf overlay\nline console\nline vty\n  exec-timeout 15\nboot kickstart bootflash:/titanium-d1-kickstart.7.3.0.D1.1.bin\nboot system bootflash:/titanium-d1.7.3.0.D1.1.bin \nip radius source-interface mgmt0\nrouter ospf underlay\n  router-id 192.168.0.18\n  passive-interface default\nrouter bgp 65003\n  router-id 192.168.0.18\n  address-family ipv4 unicast\n  address-family l2vpn evpn\n    nexthop trigger-delay critical 100 non-critical 500\n    retain route-target all\n  template peer spines\n    remote-as 65003\n    update-source loopback0\n    address-family ipv4 unicast\n    address-family l2vpn evpn\n      send-community both\n  neighbor 192.168.0.3\n    inherit peer spines\n  neighbor 192.168.0.6\n    inherit peer spines\n    address-family ipv4 unicast\n  vrf CUSTOMER-02\n    address-family ipv4 unicast\n      advertise l2vpn evpn\nevpn\n  vni 13801 l2\n    rd 6:13801\n    route-target import 1:13801\n    route-target export 1:13801\n  vni 13803 l2\n    rd 6:13803\n    route-target import 1:13803\n    route-target export 1:13803\nip tcp path-mtu-discovery\nno system default switchport shutdown\nlogging server 172.16.1.1 5 use-vrf management\nlogging server 172.16.1.2 5 use-vrf management\nlogging module 6\nlogging source-interface mgmt0\nlogging timestamp milliseconds\nlogging monitor 6",
        "ansible_net_filesystems": [
            "bootflash:"
        ],
        "ansible_net_gather_subset": [
            "hardware",
            "default",
            "interfaces",
            "legacy",
            "config"
        ],
        "ansible_net_hostname": "nx-osv-6",
        "ansible_net_image": "bootflash:///titanium-d1.7.3.0.D1.1.bin",
        "ansible_net_interfaces": {
            "Ethernet2/1": {
                "bandwidth": 1000000,
                "description": "Link to Spine-1",
                "duplex": "full",
                "ipv4": {
                    "address": "10.0.1.13",
                    "masklen": 31
                },
                "macaddress": "fa16.3e00.0017",
                "mode": "routed",
                "mtu": "9216",
                "speed": "1000 Mb/s",
                "state": "up",
                "type": "Ethernet"
            },
            "Ethernet2/10": {
                "bandwidth": 1000000,
                "duplex": "auto",
                "macaddress": "0000.0000.002f",
                "mode": "routed",
                "mtu": "1500",
                "speed": "auto-speed",
                "state": "down",
                "type": "Ethernet"
            },
            "Ethernet2/11": {
                "bandwidth": 1000000,
                "duplex": "auto",
                "macaddress": "0000.0000.002f",
                "mode": "routed",
                "mtu": "1500",
                "speed": "auto-speed",
                "state": "down",
                "type": "Ethernet"
            },
            "Ethernet2/12": {
                "bandwidth": 1000000,
                "duplex": "auto",
                "macaddress": "0000.0000.002f",
                "mode": "routed",
                "mtu": "1500",
                "speed": "auto-speed",
                "state": "down",
                "type": "Ethernet"
            },
            "Ethernet2/13": {
                "bandwidth": 1000000,
                "duplex": "auto",
                "macaddress": "0000.0000.002f",
                "mode": "routed",
                "mtu": "1500",
                "speed": "auto-speed",
                "state": "down",
                "type": "Ethernet"
            },
            "Ethernet2/14": {
                "bandwidth": 1000000,
                "duplex": "auto",
                "macaddress": "0000.0000.002f",
                "mode": "routed",
                "mtu": "1500",
                "speed": "auto-speed",
                "state": "down",
                "type": "Ethernet"
            },
            "Ethernet2/15": {
                "bandwidth": 1000000,
                "duplex": "auto",
                "macaddress": "0000.0000.002f",
                "mode": "routed",
                "mtu": "1500",
                "speed": "auto-speed",
                "state": "down",
                "type": "Ethernet"
            },
            "Ethernet2/16": {
                "bandwidth": 1000000,
                "duplex": "auto",
                "macaddress": "0000.0000.002f",
                "mode": "routed",
                "mtu": "1500",
                "speed": "auto-speed",
                "state": "down",
                "type": "Ethernet"
            },
            "Ethernet2/17": {
                "bandwidth": 1000000,
                "duplex": "auto",
                "macaddress": "0000.0000.002f",
                "mode": "routed",
                "mtu": "1500",
                "speed": "auto-speed",
                "state": "down",
                "type": "Ethernet"
            },
            "Ethernet2/18": {
                "bandwidth": 1000000,
                "duplex": "auto",
                "macaddress": "0000.0000.002f",
                "mode": "routed",
                "mtu": "1500",
                "speed": "auto-speed",
                "state": "down",
                "type": "Ethernet"
            },
            "Ethernet2/19": {
                "bandwidth": 1000000,
                "duplex": "auto",
                "macaddress": "0000.0000.002f",
                "mode": "routed",
                "mtu": "1500",
                "speed": "auto-speed",
                "state": "down",
                "type": "Ethernet"
            },
            "Ethernet2/2": {
                "bandwidth": 1000000,
                "description": "Link to Spine-2",
                "duplex": "full",
                "ipv4": {
                    "address": "10.0.2.13",
                    "masklen": 31
                },
                "macaddress": "fa16.3e00.0018",
                "mode": "routed",
                "mtu": "9216",
                "speed": "1000 Mb/s",
                "state": "up",
                "type": "Ethernet"
            },
            "Ethernet2/20": {
                "bandwidth": 1000000,
                "duplex": "auto",
                "macaddress": "0000.0000.002f",
                "mode": "routed",
                "mtu": "1500",
                "speed": "auto-speed",
                "state": "down",
                "type": "Ethernet"
            },
            "Ethernet2/21": {
                "bandwidth": 1000000,
                "duplex": "auto",
                "macaddress": "0000.0000.002f",
                "mode": "routed",
                "mtu": "1500",
                "speed": "auto-speed",
                "state": "down",
                "type": "Ethernet"
            },
            "Ethernet2/22": {
                "bandwidth": 1000000,
                "duplex": "auto",
                "macaddress": "0000.0000.002f",
                "mode": "routed",
                "mtu": "1500",
                "speed": "auto-speed",
                "state": "down",
                "type": "Ethernet"
            },
            "Ethernet2/23": {
                "bandwidth": 1000000,
                "duplex": "auto",
                "macaddress": "0000.0000.002f",
                "mode": "routed",
                "mtu": "1500",
                "speed": "auto-speed",
                "state": "down",
                "type": "Ethernet"
            },
            "Ethernet2/24": {
                "bandwidth": 1000000,
                "duplex": "auto",
                "macaddress": "0000.0000.002f",
                "mode": "routed",
                "mtu": "1500",
                "speed": "auto-speed",
                "state": "down",
                "type": "Ethernet"
            },
            "Ethernet2/25": {
                "bandwidth": 1000000,
                "duplex": "auto",
                "macaddress": "0000.0000.002f",
                "mode": "routed",
                "mtu": "1500",
                "speed": "auto-speed",
                "state": "down",
                "type": "Ethernet"
            },
            "Ethernet2/26": {
                "bandwidth": 1000000,
                "duplex": "auto",
                "macaddress": "0000.0000.002f",
                "mode": "routed",
                "mtu": "1500",
                "speed": "auto-speed",
                "state": "down",
                "type": "Ethernet"
            },
            "Ethernet2/27": {
                "bandwidth": 1000000,
                "duplex": "auto",
                "macaddress": "0000.0000.002f",
                "mode": "routed",
                "mtu": "1500",
                "speed": "auto-speed",
                "state": "down",
                "type": "Ethernet"
            },
            "Ethernet2/28": {
                "bandwidth": 1000000,
                "duplex": "auto",
                "macaddress": "0000.0000.002f",
                "mode": "routed",
                "mtu": "1500",
                "speed": "auto-speed",
                "state": "down",
                "type": "Ethernet"
            },
            "Ethernet2/29": {
                "bandwidth": 1000000,
                "duplex": "auto",
                "macaddress": "0000.0000.002f",
                "mode": "routed",
                "mtu": "1500",
                "speed": "auto-speed",
                "state": "down",
                "type": "Ethernet"
            },
            "Ethernet2/3": {
                "bandwidth": 1000000,
                "description": "ESX1",
                "duplex": "full",
                "macaddress": "fa16.3e00.0019",
                "mode": "routed",
                "mtu": "9216",
                "speed": "1000 Mb/s",
                "state": "up",
                "type": "Ethernet"
            },
            "Ethernet2/30": {
                "bandwidth": 1000000,
                "duplex": "auto",
                "macaddress": "0000.0000.002f",
                "mode": "routed",
                "mtu": "1500",
                "speed": "auto-speed",
                "state": "down",
                "type": "Ethernet"
            },
            "Ethernet2/31": {
                "bandwidth": 1000000,
                "duplex": "auto",
                "macaddress": "0000.0000.002f",
                "mode": "routed",
                "mtu": "1500",
                "speed": "auto-speed",
                "state": "down",
                "type": "Ethernet"
            },
            "Ethernet2/32": {
                "bandwidth": 1000000,
                "duplex": "auto",
                "macaddress": "0000.0000.002f",
                "mode": "routed",
                "mtu": "1500",
                "speed": "auto-speed",
                "state": "down",
                "type": "Ethernet"
            },
            "Ethernet2/33": {
                "bandwidth": 1000000,
                "duplex": "auto",
                "macaddress": "0000.0000.002f",
                "mode": "routed",
                "mtu": "1500",
                "speed": "auto-speed",
                "state": "down",
                "type": "Ethernet"
            },
            "Ethernet2/34": {
                "bandwidth": 1000000,
                "duplex": "auto",
                "macaddress": "0000.0000.002f",
                "mode": "routed",
                "mtu": "1500",
                "speed": "auto-speed",
                "state": "down",
                "type": "Ethernet"
            },
            "Ethernet2/35": {
                "bandwidth": 1000000,
                "duplex": "auto",
                "macaddress": "0000.0000.002f",
                "mode": "routed",
                "mtu": "1500",
                "speed": "auto-speed",
                "state": "down",
                "type": "Ethernet"
            },
            "Ethernet2/36": {
                "bandwidth": 1000000,
                "duplex": "auto",
                "macaddress": "0000.0000.002f",
                "mode": "routed",
                "mtu": "1500",
                "speed": "auto-speed",
                "state": "down",
                "type": "Ethernet"
            },
            "Ethernet2/37": {
                "bandwidth": 1000000,
                "duplex": "auto",
                "macaddress": "0000.0000.002f",
                "mode": "routed",
                "mtu": "1500",
                "speed": "auto-speed",
                "state": "down",
                "type": "Ethernet"
            },
            "Ethernet2/38": {
                "bandwidth": 1000000,
                "duplex": "auto",
                "macaddress": "0000.0000.002f",
                "mode": "routed",
                "mtu": "1500",
                "speed": "auto-speed",
                "state": "down",
                "type": "Ethernet"
            },
            "Ethernet2/39": {
                "bandwidth": 1000000,
                "duplex": "auto",
                "macaddress": "0000.0000.002f",
                "mode": "routed",
                "mtu": "1500",
                "speed": "auto-speed",
                "state": "down",
                "type": "Ethernet"
            },
            "Ethernet2/4": {
                "bandwidth": 1000000,
                "description": "Backup",
                "duplex": "auto",
                "macaddress": "0000.0000.002f",
                "mode": "routed",
                "mtu": "9216",
                "speed": "auto-speed",
                "state": "down",
                "type": "Ethernet"
            },
            "Ethernet2/40": {
                "bandwidth": 1000000,
                "duplex": "auto",
                "macaddress": "0000.0000.002f",
                "mode": "routed",
                "mtu": "1500",
                "speed": "auto-speed",
                "state": "down",
                "type": "Ethernet"
            },
            "Ethernet2/41": {
                "bandwidth": 1000000,
                "duplex": "auto",
                "macaddress": "0000.0000.002f",
                "mode": "routed",
                "mtu": "1500",
                "speed": "auto-speed",
                "state": "down",
                "type": "Ethernet"
            },
            "Ethernet2/42": {
                "bandwidth": 1000000,
                "duplex": "auto",
                "macaddress": "0000.0000.002f",
                "mode": "routed",
                "mtu": "1500",
                "speed": "auto-speed",
                "state": "down",
                "type": "Ethernet"
            },
            "Ethernet2/43": {
                "bandwidth": 1000000,
                "duplex": "auto",
                "macaddress": "0000.0000.002f",
                "mode": "routed",
                "mtu": "1500",
                "speed": "auto-speed",
                "state": "down",
                "type": "Ethernet"
            },
            "Ethernet2/44": {
                "bandwidth": 1000000,
                "duplex": "auto",
                "macaddress": "0000.0000.002f",
                "mode": "routed",
                "mtu": "1500",
                "speed": "auto-speed",
                "state": "down",
                "type": "Ethernet"
            },
            "Ethernet2/45": {
                "bandwidth": 1000000,
                "duplex": "auto",
                "macaddress": "0000.0000.002f",
                "mode": "routed",
                "mtu": "1500",
                "speed": "auto-speed",
                "state": "down",
                "type": "Ethernet"
            },
            "Ethernet2/46": {
                "bandwidth": 1000000,
                "duplex": "auto",
                "macaddress": "0000.0000.002f",
                "mode": "routed",
                "mtu": "1500",
                "speed": "auto-speed",
                "state": "down",
                "type": "Ethernet"
            },
            "Ethernet2/47": {
                "bandwidth": 1000000,
                "duplex": "auto",
                "macaddress": "0000.0000.002f",
                "mode": "routed",
                "mtu": "1500",
                "speed": "auto-speed",
                "state": "down",
                "type": "Ethernet"
            },
            "Ethernet2/48": {
                "bandwidth": 1000000,
                "duplex": "auto",
                "macaddress": "0000.0000.002f",
                "mode": "routed",
                "mtu": "1500",
                "speed": "auto-speed",
                "state": "down",
                "type": "Ethernet"
            },
            "Ethernet2/5": {
                "bandwidth": 1000000,
                "duplex": "auto",
                "macaddress": "0000.0000.002f",
                "mode": "routed",
                "mtu": "1500",
                "speed": "auto-speed",
                "state": "down",
                "type": "Ethernet"
            },
            "Ethernet2/6": {
                "bandwidth": 1000000,
                "duplex": "auto",
                "macaddress": "0000.0000.002f",
                "mode": "routed",
                "mtu": "1500",
                "speed": "auto-speed",
                "state": "down",
                "type": "Ethernet"
            },
            "Ethernet2/7": {
                "bandwidth": 1000000,
                "duplex": "auto",
                "macaddress": "0000.0000.002f",
                "mode": "routed",
                "mtu": "1500",
                "speed": "auto-speed",
                "state": "down",
                "type": "Ethernet"
            },
            "Ethernet2/8": {
                "bandwidth": 1000000,
                "duplex": "auto",
                "macaddress": "0000.0000.002f",
                "mode": "routed",
                "mtu": "1500",
                "speed": "auto-speed",
                "state": "down",
                "type": "Ethernet"
            },
            "Ethernet2/9": {
                "bandwidth": 1000000,
                "duplex": "auto",
                "macaddress": "0000.0000.002f",
                "mode": "routed",
                "mtu": "1500",
                "speed": "auto-speed",
                "state": "down",
                "type": "Ethernet"
            },
            "Ethernet3/1": {
                "bandwidth": 1000000,
                "duplex": "auto",
                "macaddress": "0000.0000.002f",
                "mode": "routed",
                "mtu": "1500",
                "speed": "auto-speed",
                "state": "down",
                "type": "Ethernet"
            },
            "Ethernet3/10": {
                "bandwidth": 1000000,
                "duplex": "auto",
                "macaddress": "0000.0000.002f",
                "mode": "routed",
                "mtu": "1500",
                "speed": "auto-speed",
                "state": "down",
                "type": "Ethernet"
            },
            "Ethernet3/11": {
                "bandwidth": 1000000,
                "duplex": "auto",
                "macaddress": "0000.0000.002f",
                "mode": "routed",
                "mtu": "1500",
                "speed": "auto-speed",
                "state": "down",
                "type": "Ethernet"
            },
            "Ethernet3/12": {
                "bandwidth": 1000000,
                "duplex": "auto",
                "macaddress": "0000.0000.002f",
                "mode": "routed",
                "mtu": "1500",
                "speed": "auto-speed",
                "state": "down",
                "type": "Ethernet"
            },
            "Ethernet3/13": {
                "bandwidth": 1000000,
                "duplex": "auto",
                "macaddress": "0000.0000.002f",
                "mode": "routed",
                "mtu": "1500",
                "speed": "auto-speed",
                "state": "down",
                "type": "Ethernet"
            },
            "Ethernet3/14": {
                "bandwidth": 1000000,
                "duplex": "auto",
                "macaddress": "0000.0000.002f",
                "mode": "routed",
                "mtu": "1500",
                "speed": "auto-speed",
                "state": "down",
                "type": "Ethernet"
            },
            "Ethernet3/15": {
                "bandwidth": 1000000,
                "duplex": "auto",
                "macaddress": "0000.0000.002f",
                "mode": "routed",
                "mtu": "1500",
                "speed": "auto-speed",
                "state": "down",
                "type": "Ethernet"
            },
            "Ethernet3/16": {
                "bandwidth": 1000000,
                "duplex": "auto",
                "macaddress": "0000.0000.002f",
                "mode": "routed",
                "mtu": "1500",
                "speed": "auto-speed",
                "state": "down",
                "type": "Ethernet"
            },
            "Ethernet3/17": {
                "bandwidth": 1000000,
                "duplex": "auto",
                "macaddress": "0000.0000.002f",
                "mode": "routed",
                "mtu": "1500",
                "speed": "auto-speed",
                "state": "down",
                "type": "Ethernet"
            },
            "Ethernet3/18": {
                "bandwidth": 1000000,
                "duplex": "auto",
                "macaddress": "0000.0000.002f",
                "mode": "routed",
                "mtu": "1500",
                "speed": "auto-speed",
                "state": "down",
                "type": "Ethernet"
            },
            "Ethernet3/19": {
                "bandwidth": 1000000,
                "duplex": "auto",
                "macaddress": "0000.0000.002f",
                "mode": "routed",
                "mtu": "1500",
                "speed": "auto-speed",
                "state": "down",
                "type": "Ethernet"
            },
            "Ethernet3/2": {
                "bandwidth": 1000000,
                "duplex": "auto",
                "macaddress": "0000.0000.002f",
                "mode": "routed",
                "mtu": "1500",
                "speed": "auto-speed",
                "state": "down",
                "type": "Ethernet"
            },
            "Ethernet3/20": {
                "bandwidth": 1000000,
                "duplex": "auto",
                "macaddress": "0000.0000.002f",
                "mode": "routed",
                "mtu": "1500",
                "speed": "auto-speed",
                "state": "down",
                "type": "Ethernet"
            },
            "Ethernet3/21": {
                "bandwidth": 1000000,
                "duplex": "auto",
                "macaddress": "0000.0000.002f",
                "mode": "routed",
                "mtu": "1500",
                "speed": "auto-speed",
                "state": "down",
                "type": "Ethernet"
            },
            "Ethernet3/22": {
                "bandwidth": 1000000,
                "duplex": "auto",
                "macaddress": "0000.0000.002f",
                "mode": "routed",
                "mtu": "1500",
                "speed": "auto-speed",
                "state": "down",
                "type": "Ethernet"
            },
            "Ethernet3/23": {
                "bandwidth": 1000000,
                "duplex": "auto",
                "macaddress": "0000.0000.002f",
                "mode": "routed",
                "mtu": "1500",
                "speed": "auto-speed",
                "state": "down",
                "type": "Ethernet"
            },
            "Ethernet3/24": {
                "bandwidth": 1000000,
                "duplex": "auto",
                "macaddress": "0000.0000.002f",
                "mode": "routed",
                "mtu": "1500",
                "speed": "auto-speed",
                "state": "down",
                "type": "Ethernet"
            },
            "Ethernet3/25": {
                "bandwidth": 1000000,
                "duplex": "auto",
                "macaddress": "0000.0000.002f",
                "mode": "routed",
                "mtu": "1500",
                "speed": "auto-speed",
                "state": "down",
                "type": "Ethernet"
            },
            "Ethernet3/26": {
                "bandwidth": 1000000,
                "duplex": "auto",
                "macaddress": "0000.0000.002f",
                "mode": "routed",
                "mtu": "1500",
                "speed": "auto-speed",
                "state": "down",
                "type": "Ethernet"
            },
            "Ethernet3/27": {
                "bandwidth": 1000000,
                "duplex": "auto",
                "macaddress": "0000.0000.002f",
                "mode": "routed",
                "mtu": "1500",
                "speed": "auto-speed",
                "state": "down",
                "type": "Ethernet"
            },
            "Ethernet3/28": {
                "bandwidth": 1000000,
                "duplex": "auto",
                "macaddress": "0000.0000.002f",
                "mode": "routed",
                "mtu": "1500",
                "speed": "auto-speed",
                "state": "down",
                "type": "Ethernet"
            },
            "Ethernet3/29": {
                "bandwidth": 1000000,
                "duplex": "auto",
                "macaddress": "0000.0000.002f",
                "mode": "routed",
                "mtu": "1500",
                "speed": "auto-speed",
                "state": "down",
                "type": "Ethernet"
            },
            "Ethernet3/3": {
                "bandwidth": 1000000,
                "duplex": "auto",
                "macaddress": "0000.0000.002f",
                "mode": "routed",
                "mtu": "1500",
                "speed": "auto-speed",
                "state": "down",
                "type": "Ethernet"
            },
            "Ethernet3/30": {
                "bandwidth": 1000000,
                "duplex": "auto",
                "macaddress": "0000.0000.002f",
                "mode": "routed",
                "mtu": "1500",
                "speed": "auto-speed",
                "state": "down",
                "type": "Ethernet"
            },
            "Ethernet3/31": {
                "bandwidth": 1000000,
                "duplex": "auto",
                "macaddress": "0000.0000.002f",
                "mode": "routed",
                "mtu": "1500",
                "speed": "auto-speed",
                "state": "down",
                "type": "Ethernet"
            },
            "Ethernet3/32": {
                "bandwidth": 1000000,
                "duplex": "auto",
                "macaddress": "0000.0000.002f",
                "mode": "routed",
                "mtu": "1500",
                "speed": "auto-speed",
                "state": "down",
                "type": "Ethernet"
            },
            "Ethernet3/33": {
                "bandwidth": 1000000,
                "duplex": "auto",
                "macaddress": "0000.0000.002f",
                "mode": "routed",
                "mtu": "1500",
                "speed": "auto-speed",
                "state": "down",
                "type": "Ethernet"
            },
            "Ethernet3/34": {
                "bandwidth": 1000000,
                "duplex": "auto",
                "macaddress": "0000.0000.002f",
                "mode": "routed",
                "mtu": "1500",
                "speed": "auto-speed",
                "state": "down",
                "type": "Ethernet"
            },
            "Ethernet3/35": {
                "bandwidth": 1000000,
                "duplex": "auto",
                "macaddress": "0000.0000.002f",
                "mode": "routed",
                "mtu": "1500",
                "speed": "auto-speed",
                "state": "down",
                "type": "Ethernet"
            },
            "Ethernet3/36": {
                "bandwidth": 1000000,
                "duplex": "auto",
                "macaddress": "0000.0000.002f",
                "mode": "routed",
                "mtu": "1500",
                "speed": "auto-speed",
                "state": "down",
                "type": "Ethernet"
            },
            "Ethernet3/37": {
                "bandwidth": 1000000,
                "duplex": "auto",
                "macaddress": "0000.0000.002f",
                "mode": "routed",
                "mtu": "1500",
                "speed": "auto-speed",
                "state": "down",
                "type": "Ethernet"
            },
            "Ethernet3/38": {
                "bandwidth": 1000000,
                "duplex": "auto",
                "macaddress": "0000.0000.002f",
                "mode": "routed",
                "mtu": "1500",
                "speed": "auto-speed",
                "state": "down",
                "type": "Ethernet"
            },
            "Ethernet3/39": {
                "bandwidth": 1000000,
                "duplex": "auto",
                "macaddress": "0000.0000.002f",
                "mode": "routed",
                "mtu": "1500",
                "speed": "auto-speed",
                "state": "down",
                "type": "Ethernet"
            },
            "Ethernet3/4": {
                "bandwidth": 1000000,
                "duplex": "auto",
                "macaddress": "0000.0000.002f",
                "mode": "routed",
                "mtu": "1500",
                "speed": "auto-speed",
                "state": "down",
                "type": "Ethernet"
            },
            "Ethernet3/40": {
                "bandwidth": 1000000,
                "duplex": "auto",
                "macaddress": "0000.0000.002f",
                "mode": "routed",
                "mtu": "1500",
                "speed": "auto-speed",
                "state": "down",
                "type": "Ethernet"
            },
            "Ethernet3/41": {
                "bandwidth": 1000000,
                "duplex": "auto",
                "macaddress": "0000.0000.002f",
                "mode": "routed",
                "mtu": "1500",
                "speed": "auto-speed",
                "state": "down",
                "type": "Ethernet"
            },
            "Ethernet3/42": {
                "bandwidth": 1000000,
                "duplex": "auto",
                "macaddress": "0000.0000.002f",
                "mode": "routed",
                "mtu": "1500",
                "speed": "auto-speed",
                "state": "down",
                "type": "Ethernet"
            },
            "Ethernet3/43": {
                "bandwidth": 1000000,
                "duplex": "auto",
                "macaddress": "0000.0000.002f",
                "mode": "routed",
                "mtu": "1500",
                "speed": "auto-speed",
                "state": "down",
                "type": "Ethernet"
            },
            "Ethernet3/44": {
                "bandwidth": 1000000,
                "duplex": "auto",
                "macaddress": "0000.0000.002f",
                "mode": "routed",
                "mtu": "1500",
                "speed": "auto-speed",
                "state": "down",
                "type": "Ethernet"
            },
            "Ethernet3/45": {
                "bandwidth": 1000000,
                "duplex": "auto",
                "macaddress": "0000.0000.002f",
                "mode": "routed",
                "mtu": "1500",
                "speed": "auto-speed",
                "state": "down",
                "type": "Ethernet"
            },
            "Ethernet3/46": {
                "bandwidth": 1000000,
                "duplex": "auto",
                "macaddress": "0000.0000.002f",
                "mode": "routed",
                "mtu": "1500",
                "speed": "auto-speed",
                "state": "down",
                "type": "Ethernet"
            },
            "Ethernet3/47": {
                "bandwidth": 1000000,
                "duplex": "auto",
                "macaddress": "0000.0000.002f",
                "mode": "routed",
                "mtu": "1500",
                "speed": "auto-speed",
                "state": "down",
                "type": "Ethernet"
            },
            "Ethernet3/48": {
                "bandwidth": 1000000,
                "duplex": "auto",
                "macaddress": "0000.0000.002f",
                "mode": "routed",
                "mtu": "1500",
                "speed": "auto-speed",
                "state": "down",
                "type": "Ethernet"
            },
            "Ethernet3/5": {
                "bandwidth": 1000000,
                "duplex": "auto",
                "macaddress": "0000.0000.002f",
                "mode": "routed",
                "mtu": "1500",
                "speed": "auto-speed",
                "state": "down",
                "type": "Ethernet"
            },
            "Ethernet3/6": {
                "bandwidth": 1000000,
                "duplex": "auto",
                "macaddress": "0000.0000.002f",
                "mode": "routed",
                "mtu": "1500",
                "speed": "auto-speed",
                "state": "down",
                "type": "Ethernet"
            },
            "Ethernet3/7": {
                "bandwidth": 1000000,
                "duplex": "auto",
                "macaddress": "0000.0000.002f",
                "mode": "routed",
                "mtu": "1500",
                "speed": "auto-speed",
                "state": "down",
                "type": "Ethernet"
            },
            "Ethernet3/8": {
                "bandwidth": 1000000,
                "duplex": "auto",
                "macaddress": "0000.0000.002f",
                "mode": "routed",
                "mtu": "1500",
                "speed": "auto-speed",
                "state": "down",
                "type": "Ethernet"
            },
            "Ethernet3/9": {
                "bandwidth": 1000000,
                "duplex": "auto",
                "macaddress": "0000.0000.002f",
                "mode": "routed",
                "mtu": "1500",
                "speed": "auto-speed",
                "state": "down",
                "type": "Ethernet"
            },
            "Ethernet4/1": {
                "bandwidth": 1000000,
                "duplex": "auto",
                "macaddress": "0000.0000.002f",
                "mode": "routed",
                "mtu": "1500",
                "speed": "auto-speed",
                "state": "down",
                "type": "Ethernet"
            },
            "Ethernet4/10": {
                "bandwidth": 1000000,
                "duplex": "auto",
                "macaddress": "0000.0000.002f",
                "mode": "routed",
                "mtu": "1500",
                "speed": "auto-speed",
                "state": "down",
                "type": "Ethernet"
            },
            "Ethernet4/11": {
                "bandwidth": 1000000,
                "duplex": "auto",
                "macaddress": "0000.0000.002f",
                "mode": "routed",
                "mtu": "1500",
                "speed": "auto-speed",
                "state": "down",
                "type": "Ethernet"
            },
            "Ethernet4/12": {
                "bandwidth": 1000000,
                "duplex": "auto",
                "macaddress": "0000.0000.002f",
                "mode": "routed",
                "mtu": "1500",
                "speed": "auto-speed",
                "state": "down",
                "type": "Ethernet"
            },
            "Ethernet4/13": {
                "bandwidth": 1000000,
                "duplex": "auto",
                "macaddress": "0000.0000.002f",
                "mode": "routed",
                "mtu": "1500",
                "speed": "auto-speed",
                "state": "down",
                "type": "Ethernet"
            },
            "Ethernet4/14": {
                "bandwidth": 1000000,
                "duplex": "auto",
                "macaddress": "0000.0000.002f",
                "mode": "routed",
                "mtu": "1500",
                "speed": "auto-speed",
                "state": "down",
                "type": "Ethernet"
            },
            "Ethernet4/15": {
                "bandwidth": 1000000,
                "duplex": "auto",
                "macaddress": "0000.0000.002f",
                "mode": "routed",
                "mtu": "1500",
                "speed": "auto-speed",
                "state": "down",
                "type": "Ethernet"
            },
            "Ethernet4/16": {
                "bandwidth": 1000000,
                "duplex": "auto",
                "macaddress": "0000.0000.002f",
                "mode": "routed",
                "mtu": "1500",
                "speed": "auto-speed",
                "state": "down",
                "type": "Ethernet"
            },
            "Ethernet4/17": {
                "bandwidth": 1000000,
                "duplex": "auto",
                "macaddress": "0000.0000.002f",
                "mode": "routed",
                "mtu": "1500",
                "speed": "auto-speed",
                "state": "down",
                "type": "Ethernet"
            },
            "Ethernet4/18": {
                "bandwidth": 1000000,
                "duplex": "auto",
                "macaddress": "0000.0000.002f",
                "mode": "routed",
                "mtu": "1500",
                "speed": "auto-speed",
                "state": "down",
                "type": "Ethernet"
            },
            "Ethernet4/19": {
                "bandwidth": 1000000,
                "duplex": "auto",
                "macaddress": "0000.0000.002f",
                "mode": "routed",
                "mtu": "1500",
                "speed": "auto-speed",
                "state": "down",
                "type": "Ethernet"
            },
            "Ethernet4/2": {
                "bandwidth": 1000000,
                "duplex": "auto",
                "macaddress": "0000.0000.002f",
                "mode": "routed",
                "mtu": "1500",
                "speed": "auto-speed",
                "state": "down",
                "type": "Ethernet"
            },
            "Ethernet4/20": {
                "bandwidth": 1000000,
                "duplex": "auto",
                "macaddress": "0000.0000.002f",
                "mode": "routed",
                "mtu": "1500",
                "speed": "auto-speed",
                "state": "down",
                "type": "Ethernet"
            },
            "Ethernet4/21": {
                "bandwidth": 1000000,
                "duplex": "auto",
                "macaddress": "0000.0000.002f",
                "mode": "routed",
                "mtu": "1500",
                "speed": "auto-speed",
                "state": "down",
                "type": "Ethernet"
            },
            "Ethernet4/22": {
                "bandwidth": 1000000,
                "duplex": "auto",
                "macaddress": "0000.0000.002f",
                "mode": "routed",
                "mtu": "1500",
                "speed": "auto-speed",
                "state": "down",
                "type": "Ethernet"
            },
            "Ethernet4/23": {
                "bandwidth": 1000000,
                "duplex": "auto",
                "macaddress": "0000.0000.002f",
                "mode": "routed",
                "mtu": "1500",
                "speed": "auto-speed",
                "state": "down",
                "type": "Ethernet"
            },
            "Ethernet4/24": {
                "bandwidth": 1000000,
                "duplex": "auto",
                "macaddress": "0000.0000.002f",
                "mode": "routed",
                "mtu": "1500",
                "speed": "auto-speed",
                "state": "down",
                "type": "Ethernet"
            },
            "Ethernet4/25": {
                "bandwidth": 1000000,
                "duplex": "auto",
                "macaddress": "0000.0000.002f",
                "mode": "routed",
                "mtu": "1500",
                "speed": "auto-speed",
                "state": "down",
                "type": "Ethernet"
            },
            "Ethernet4/26": {
                "bandwidth": 1000000,
                "duplex": "auto",
                "macaddress": "0000.0000.002f",
                "mode": "routed",
                "mtu": "1500",
                "speed": "auto-speed",
                "state": "down",
                "type": "Ethernet"
            },
            "Ethernet4/27": {
                "bandwidth": 1000000,
                "duplex": "auto",
                "macaddress": "0000.0000.002f",
                "mode": "routed",
                "mtu": "1500",
                "speed": "auto-speed",
                "state": "down",
                "type": "Ethernet"
            },
            "Ethernet4/28": {
                "bandwidth": 1000000,
                "duplex": "auto",
                "macaddress": "0000.0000.002f",
                "mode": "routed",
                "mtu": "1500",
                "speed": "auto-speed",
                "state": "down",
                "type": "Ethernet"
            },
            "Ethernet4/29": {
                "bandwidth": 1000000,
                "duplex": "auto",
                "macaddress": "0000.0000.002f",
                "mode": "routed",
                "mtu": "1500",
                "speed": "auto-speed",
                "state": "down",
                "type": "Ethernet"
            },
            "Ethernet4/3": {
                "bandwidth": 1000000,
                "duplex": "auto",
                "macaddress": "0000.0000.002f",
                "mode": "routed",
                "mtu": "1500",
                "speed": "auto-speed",
                "state": "down",
                "type": "Ethernet"
            },
            "Ethernet4/30": {
                "bandwidth": 1000000,
                "duplex": "auto",
                "macaddress": "0000.0000.002f",
                "mode": "routed",
                "mtu": "1500",
                "speed": "auto-speed",
                "state": "down",
                "type": "Ethernet"
            },
            "Ethernet4/31": {
                "bandwidth": 1000000,
                "duplex": "auto",
                "macaddress": "0000.0000.002f",
                "mode": "routed",
                "mtu": "1500",
                "speed": "auto-speed",
                "state": "down",
                "type": "Ethernet"
            },
            "Ethernet4/32": {
                "bandwidth": 1000000,
                "duplex": "auto",
                "macaddress": "0000.0000.002f",
                "mode": "routed",
                "mtu": "1500",
                "speed": "auto-speed",
                "state": "down",
                "type": "Ethernet"
            },
            "Ethernet4/33": {
                "bandwidth": 1000000,
                "duplex": "auto",
                "macaddress": "0000.0000.002f",
                "mode": "routed",
                "mtu": "1500",
                "speed": "auto-speed",
                "state": "down",
                "type": "Ethernet"
            },
            "Ethernet4/34": {
                "bandwidth": 1000000,
                "duplex": "auto",
                "macaddress": "0000.0000.002f",
                "mode": "routed",
                "mtu": "1500",
                "speed": "auto-speed",
                "state": "down",
                "type": "Ethernet"
            },
            "Ethernet4/35": {
                "bandwidth": 1000000,
                "duplex": "auto",
                "macaddress": "0000.0000.002f",
                "mode": "routed",
                "mtu": "1500",
                "speed": "auto-speed",
                "state": "down",
                "type": "Ethernet"
            },
            "Ethernet4/36": {
                "bandwidth": 1000000,
                "duplex": "auto",
                "macaddress": "0000.0000.002f",
                "mode": "routed",
                "mtu": "1500",
                "speed": "auto-speed",
                "state": "down",
                "type": "Ethernet"
            },
            "Ethernet4/37": {
                "bandwidth": 1000000,
                "duplex": "auto",
                "macaddress": "0000.0000.002f",
                "mode": "routed",
                "mtu": "1500",
                "speed": "auto-speed",
                "state": "down",
                "type": "Ethernet"
            },
            "Ethernet4/38": {
                "bandwidth": 1000000,
                "duplex": "auto",
                "macaddress": "0000.0000.002f",
                "mode": "routed",
                "mtu": "1500",
                "speed": "auto-speed",
                "state": "down",
                "type": "Ethernet"
            },
            "Ethernet4/39": {
                "bandwidth": 1000000,
                "duplex": "auto",
                "macaddress": "0000.0000.002f",
                "mode": "routed",
                "mtu": "1500",
                "speed": "auto-speed",
                "state": "down",
                "type": "Ethernet"
            },
            "Ethernet4/4": {
                "bandwidth": 1000000,
                "duplex": "auto",
                "macaddress": "0000.0000.002f",
                "mode": "routed",
                "mtu": "1500",
                "speed": "auto-speed",
                "state": "down",
                "type": "Ethernet"
            },
            "Ethernet4/40": {
                "bandwidth": 1000000,
                "duplex": "auto",
                "macaddress": "0000.0000.002f",
                "mode": "routed",
                "mtu": "1500",
                "speed": "auto-speed",
                "state": "down",
                "type": "Ethernet"
            },
            "Ethernet4/41": {
                "bandwidth": 1000000,
                "duplex": "auto",
                "macaddress": "0000.0000.002f",
                "mode": "routed",
                "mtu": "1500",
                "speed": "auto-speed",
                "state": "down",
                "type": "Ethernet"
            },
            "Ethernet4/42": {
                "bandwidth": 1000000,
                "duplex": "auto",
                "macaddress": "0000.0000.002f",
                "mode": "routed",
                "mtu": "1500",
                "speed": "auto-speed",
                "state": "down",
                "type": "Ethernet"
            },
            "Ethernet4/43": {
                "bandwidth": 1000000,
                "duplex": "auto",
                "macaddress": "0000.0000.002f",
                "mode": "routed",
                "mtu": "1500",
                "speed": "auto-speed",
                "state": "down",
                "type": "Ethernet"
            },
            "Ethernet4/44": {
                "bandwidth": 1000000,
                "duplex": "auto",
                "macaddress": "0000.0000.002f",
                "mode": "routed",
                "mtu": "1500",
                "speed": "auto-speed",
                "state": "down",
                "type": "Ethernet"
            },
            "Ethernet4/45": {
                "bandwidth": 1000000,
                "duplex": "auto",
                "macaddress": "0000.0000.002f",
                "mode": "routed",
                "mtu": "1500",
                "speed": "auto-speed",
                "state": "down",
                "type": "Ethernet"
            },
            "Ethernet4/46": {
                "bandwidth": 1000000,
                "duplex": "auto",
                "macaddress": "0000.0000.002f",
                "mode": "routed",
                "mtu": "1500",
                "speed": "auto-speed",
                "state": "down",
                "type": "Ethernet"
            },
            "Ethernet4/47": {
                "bandwidth": 1000000,
                "duplex": "auto",
                "macaddress": "0000.0000.002f",
                "mode": "routed",
                "mtu": "1500",
                "speed": "auto-speed",
                "state": "down",
                "type": "Ethernet"
            },
            "Ethernet4/48": {
                "bandwidth": 1000000,
                "duplex": "auto",
                "macaddress": "0000.0000.002f",
                "mode": "routed",
                "mtu": "1500",
                "speed": "auto-speed",
                "state": "down",
                "type": "Ethernet"
            },
            "Ethernet4/5": {
                "bandwidth": 1000000,
                "duplex": "auto",
                "macaddress": "0000.0000.002f",
                "mode": "routed",
                "mtu": "1500",
                "speed": "auto-speed",
                "state": "down",
                "type": "Ethernet"
            },
            "Ethernet4/6": {
                "bandwidth": 1000000,
                "duplex": "auto",
                "macaddress": "0000.0000.002f",
                "mode": "routed",
                "mtu": "1500",
                "speed": "auto-speed",
                "state": "down",
                "type": "Ethernet"
            },
            "Ethernet4/7": {
                "bandwidth": 1000000,
                "duplex": "auto",
                "macaddress": "0000.0000.002f",
                "mode": "routed",
                "mtu": "1500",
                "speed": "auto-speed",
                "state": "down",
                "type": "Ethernet"
            },
            "Ethernet4/8": {
                "bandwidth": 1000000,
                "duplex": "auto",
                "macaddress": "0000.0000.002f",
                "mode": "routed",
                "mtu": "1500",
                "speed": "auto-speed",
                "state": "down",
                "type": "Ethernet"
            },
            "Ethernet4/9": {
                "bandwidth": 1000000,
                "duplex": "auto",
                "macaddress": "0000.0000.002f",
                "mode": "routed",
                "mtu": "1500",
                "speed": "auto-speed",
                "state": "down",
                "type": "Ethernet"
            },
            "Vlan1": {
                "bandwidth": "1000000",
                "macaddress": "fa16.3e98.7ab1",
                "mtu": "1500",
                "state": "down",
                "type": "svi"
            },
            "Vlan1001": {
                "bandwidth": "1000000",
                "macaddress": "fa16.3e98.7ab1",
                "mtu": "9216",
                "state": "down",
                "type": "svi"
            },
            "Vlan3803": {
                "bandwidth": "1000000",
                "ipv4": {
                    "address": "192.168.0.1",
                    "masklen": "24"
                },
                "macaddress": "fa16.3e98.7ab1",
                "mtu": "9100",
                "state": "down",
                "type": "svi"
            },
            "loopback0": {
                "bandwidth": 8000000,
                "description": "Loopback",
                "ipv4": {
                    "address": "192.168.0.18",
                    "masklen": 24
                },
                "mode": "routed",
                "mtu": "1500",
                "state": "up",
                "type": "Loopback"
            },
            "mgmt0": {
                "bandwidth": 1000000,
                "description": "OOB Management",
                "duplex": "full",
                "ipv4": {
                    "address": "172.16.1.15",
                    "masklen": 24
                },
                "macaddress": "5e00.0007.0000",
                "mode": "routed",
                "mtu": "1500",
                "speed": "1000 Mb/s",
                "state": "up",
                "type": "Ethernet"
            },
            "nve1": {
                "state": "up",
                "type": "NVE"
            }
        },
        "ansible_net_memfree_mb": 676,
        "ansible_net_memtotal_mb": 2992,
        "ansible_net_model": "NX-OSv Chassis",
        "ansible_net_neighbors": {
            "Ethernet2/1": [
                {
                    "port": "Ethernet2/4",
                    "sysname": "nx-osv-1(TB00000000B)"
                }
            ],
            "Ethernet2/2": [
                {
                    "port": "Ethernet2/4",
                    "sysname": "nx-osv-2(TB00010000B)"
                }
            ],
            "mgmt0": [
                {
                    "port": "mgmt0",
                    "sysname": "nx-osv-3(TB00020000B)"
                }
            ]
        },
        "ansible_net_serialnum": "TM00070000B",
        "ansible_net_version": "7.3(0)D1(1)",
        "fan_info": [
            {
                "hw_ver": "0.0",
                "model": null,
                "name": "ChassisFan1",
                "status": "Ok"
            },
            {
                "hw_ver": "0.0",
                "model": null,
                "name": "ChassisFan2",
                "status": "None"
            },
            {
                "hw_ver": "--",
                "model": "--",
                "name": "Fan_in_PS1",
                "status": "Ok"
            },
            {
                "hw_ver": "--",
                "model": "--",
                "name": "Fan_in_PS2",
                "status": "Failure"
            }
        ],
        "hostname": "nx-osv-6",
        "interfaces_list": [
            "mgmt0",
            "Ethernet2/1",
            "Ethernet2/2",
            "Ethernet2/3",
            "Ethernet2/4",
            "Ethernet2/5",
            "Ethernet2/6",
            "Ethernet2/7",
            "Ethernet2/8",
            "Ethernet2/9",
            "Ethernet2/10",
            "Ethernet2/11",
            "Ethernet2/12",
            "Ethernet2/13",
            "Ethernet2/14",
            "Ethernet2/15",
            "Ethernet2/16",
            "Ethernet2/17",
            "Ethernet2/18",
            "Ethernet2/19",
            "Ethernet2/20",
            "Ethernet2/21",
            "Ethernet2/22",
            "Ethernet2/23",
            "Ethernet2/24",
            "Ethernet2/25",
            "Ethernet2/26",
            "Ethernet2/27",
            "Ethernet2/28",
            "Ethernet2/29",
            "Ethernet2/30",
            "Ethernet2/31",
            "Ethernet2/32",
            "Ethernet2/33",
            "Ethernet2/34",
            "Ethernet2/35",
            "Ethernet2/36",
            "Ethernet2/37",
            "Ethernet2/38",
            "Ethernet2/39",
            "Ethernet2/40",
            "Ethernet2/41",
            "Ethernet2/42",
            "Ethernet2/43",
            "Ethernet2/44",
            "Ethernet2/45",
            "Ethernet2/46",
            "Ethernet2/47",
            "Ethernet2/48",
            "Ethernet3/1",
            "Ethernet3/2",
            "Ethernet3/3",
            "Ethernet3/4",
            "Ethernet3/5",
            "Ethernet3/6",
            "Ethernet3/7",
            "Ethernet3/8",
            "Ethernet3/9",
            "Ethernet3/10",
            "Ethernet3/11",
            "Ethernet3/12",
            "Ethernet3/13",
            "Ethernet3/14",
            "Ethernet3/15",
            "Ethernet3/16",
            "Ethernet3/17",
            "Ethernet3/18",
            "Ethernet3/19",
            "Ethernet3/20",
            "Ethernet3/21",
            "Ethernet3/22",
            "Ethernet3/23",
            "Ethernet3/24",
            "Ethernet3/25",
            "Ethernet3/26",
            "Ethernet3/27",
            "Ethernet3/28",
            "Ethernet3/29",
            "Ethernet3/30",
            "Ethernet3/31",
            "Ethernet3/32",
            "Ethernet3/33",
            "Ethernet3/34",
            "Ethernet3/35",
            "Ethernet3/36",
            "Ethernet3/37",
            "Ethernet3/38",
            "Ethernet3/39",
            "Ethernet3/40",
            "Ethernet3/41",
            "Ethernet3/42",
            "Ethernet3/43",
            "Ethernet3/44",
            "Ethernet3/45",
            "Ethernet3/46",
            "Ethernet3/47",
            "Ethernet3/48",
            "Ethernet4/1",
            "Ethernet4/2",
            "Ethernet4/3",
            "Ethernet4/4",
            "Ethernet4/5",
            "Ethernet4/6",
            "Ethernet4/7",
            "Ethernet4/8",
            "Ethernet4/9",
            "Ethernet4/10",
            "Ethernet4/11",
            "Ethernet4/12",
            "Ethernet4/13",
            "Ethernet4/14",
            "Ethernet4/15",
            "Ethernet4/16",
            "Ethernet4/17",
            "Ethernet4/18",
            "Ethernet4/19",
            "Ethernet4/20",
            "Ethernet4/21",
            "Ethernet4/22",
            "Ethernet4/23",
            "Ethernet4/24",
            "Ethernet4/25",
            "Ethernet4/26",
            "Ethernet4/27",
            "Ethernet4/28",
            "Ethernet4/29",
            "Ethernet4/30",
            "Ethernet4/31",
            "Ethernet4/32",
            "Ethernet4/33",
            "Ethernet4/34",
            "Ethernet4/35",
            "Ethernet4/36",
            "Ethernet4/37",
            "Ethernet4/38",
            "Ethernet4/39",
            "Ethernet4/40",
            "Ethernet4/41",
            "Ethernet4/42",
            "Ethernet4/43",
            "Ethernet4/44",
            "Ethernet4/45",
            "Ethernet4/46",
            "Ethernet4/47",
            "Ethernet4/48",
            "loopback0",
            "Vlan1",
            "Vlan1001",
            "Vlan3803",
            "nve1"
        ],
        "module": [
            {
                "model": "N7K-SUP1",
                "ports": 0,
                "status": "active *",
                "type": "NX-OSv Supervisor Module"
            },
            {
                "model": "N7K-F248XP-25",
                "ports": 48,
                "status": "ok",
                "type": "NX-OSv Ethernet Module"
            },
            {
                "model": "N7K-F248XP-25",
                "ports": 48,
                "status": "ok",
                "type": "NX-OSv Ethernet Module"
            },
            {
                "model": "N7K-F248XP-25",
                "ports": 48,
                "status": "ok",
                "type": "NX-OSv Ethernet Module"
            }
        ],
        "os": "7.3(0)D1(1)",
        "platform": "NX-OSv Chassis",
        "power_supply_info": [
            {
                "amps": "77.96",
                "model": "DS-CAC-845W",
                "number": 1,
                "status": "Ok",
                "watts": "3274.32"
            },
            {
                "amps": "0.00",
                "model": "------------",
                "number": 2,
                "status": "Absent",
                "watts": "0.00"
            }
        ],
        "vlan_list": [
            1,
            1001,
            3801,
            3803
        ]
    },
    "changed": false,
    "failed": false
}